Workbook

Sheet MFModRaw
B1: KHMNYGDPMKTPKN_0 | C1: KHMNYGDPMKTPKN_111 | D1: KHMNYGDPMKTPKN_112 | E1: KHMNYGDPMKTPKN_113 | F1: KHMNYGDPMKTPKN_114 | G1: KHMNYGDPMKTPKN_121 | H1: KHMNYGDPMKTPKN_122 | I1: KHMNYGDPMKTPKN_123 | J1: KHMNYGDPMKTPKN_124 | K1: KHMNYGDPMKTPKN_131 | L1: KHMNYGDPMKTPKN_132 | M1: KHMNYGDPMKTPKN_133 | N1: KHMNYGDPMKTPKN_134 | O1: KHMNYGDPMKTPKN_211 | P1: KHMNYGDPMKTPKN_212 | Q1: KHMNYGDPMKTPKN_213 | R1: KHMNYGDPMKTPKN_214 | S1: KHMNYGDPMKTPKN_221 | T1: KHMNYGDPMKTPKN_222 | U1: KHMNYGDPMKTPKN_223 | V1: KHMNYGDPMKTPKN_224 | W1: KHMNYGDPMKTPKN_231 | X1: KHMNYGDPMKTPKN_232 | Y1: KHMNYGDPMKTPKN_233 | Z1: KHMNYGDPMKTPKN_234
A2: 2015 | B2: 95406125 | C2: 95406125 | D2: 95406125 | E2: 95406125 | F2: 95406125 | G2: 95406125 | H2: 95406125 | I2: 95406125 | J2: 95406125 | K2: 95406125 | L2: 95406125 | M2: 95406125 | N2: 95406125 | O2: 95406125 | P2: 95406125 | Q2: 95406125 | R2: 95406125 | S2: 95406125 | T2: 95406125 | U2: 95406125 | V2: 95406125 | W2: 95406125 | X2: 95406125 | Y2: 95406125 | Z2: 95406125
A3: 2016 | B3: 1.0294846e+08 | C3: 1.0294846e+08 | D3: 1.0294846e+08 | E3: 1.0294846e+08 | F3: 1.0294846e+08 | G3: 1.0294846e+08 | H3: 1.0294846e+08 | I3: 1.0294846e+08 | J3: 1.0294846e+08 | K3: 1.0294846e+08 | L3: 1.0294846e+08 | M3: 1.0294846e+08 | N3: 1.0294846e+08 | O3: 1.0294846e+08 | P3: 1.0294846e+08 | Q3: 1.0294846e+08 | R3: 1.0294846e+08 | S3: 1.0294846e+08 | T3: 1.0294846e+08 | U3: 1.0294846e+08 | V3: 1.0294846e+08 | W3: 1.0294846e+08 | X3: 1.0294846e+08 | Y3: 1.0294846e+08 | Z3: 1.0294846e+08
A4: 2017 | B4: 1.1126159e+08 | C4: 1.1126159e+08 | D4: 1.1126159e+08 | E4: 1.1126159e+08 | F4: 1.1126159e+08 | G4: 1.1126159e+08 | H4: 1.1126159e+08 | I4: 1.1126159e+08 | J4: 1.1126159e+08 | K4: 1.1126159e+08 | L4: 1.1126159e+08 | M4: 1.1126159e+08 | N4: 1.1126159e+08 | O4: 1.1126159e+08 | P4: 1.1126159e+08 | Q4: 1.1126159e+08 | R4: 1.1126159e+08 | S4: 1.1126159e+08 | T4: 1.1126159e+08 | U4: 1.1126159e+08 | V4: 1.1126159e+08 | W4: 1.1126159e+08 | X4: 1.1126159e+08 | Y4: 1.1126159e+08 | Z4: 1.1126159e+08
A5: 2018 | B5: 1.2102615e+08 | C5: 1.2102615e+08 | D5: 1.2102615e+08 | E5: 1.2102615e+08 | F5: 1.2102615e+08 | G5: 1.2102615e+08 | H5: 1.2102615e+08 | I5: 1.2102615e+08 | J5: 1.2102615e+08 | K5: 1.2102615e+08 | L5: 1.2102615e+08 | M5: 1.2102615e+08 | N5: 1.2102615e+08 | O5: 1.2102615e+08 | P5: 1.2102615e+08 | Q5: 1.2102615e+08 | R5: 1.2102615e+08 | S5: 1.2102615e+08 | T5: 1.2102615e+08 | U5: 1.2102615e+08 | V5: 1.2102615e+08 | W5: 1.2102615e+08 | X5: 1.2102615e+08 | Y5: 1.2102615e+08 | Z5: 1.2102615e+08
A6: 2019 | B6: 1.3063194e+08 | C6: 1.3063194e+08 | D6: 1.3063194e+08 | E6: 1.3063194e+08 | F6: 1.3063194e+08 | G6: 1.3063194e+08 | H6: 1.3063194e+08 | I6: 1.3063194e+08 | J6: 1.3063194e+08 | K6: 1.3063194e+08 | L6: 1.3063194e+08 | M6: 1.3063194e+08 | N6: 1.3063194e+08 | O6: 1.3063194e+08 | P6: 1.3063194e+08 | Q6: 1.3063194e+08 | R6: 1.3063194e+08 | S6: 1.3063194e+08 | T6: 1.3063194e+08 | U6: 1.3063194e+08 | V6: 1.3063194e+08 | W6: 1.3063194e+08 | X6: 1.3063194e+08 | Y6: 1.3063194e+08 | Z6: 1.3063194e+08
A7: 2020 | B7: 1.2598703e+08 | C7: 1.2598703e+08 | D7: 1.2598703e+08 | E7: 1.2598703e+08 | F7: 1.2598703e+08 | G7: 1.2598715e+08 | H7: 1.2598715e+08 | I7: 1.2598715e+08 | J7: 1.2598715e+08 | K7: 1.2598728e+08 | L7: 1.2598728e+08 | M7: 1.2598728e+08 | N7: 1.2598728e+08 | O7: 1.2598703e+08 | P7: 1.2598703e+08 | Q7: 1.2598703e+08 | R7: 1.2598703e+08 | S7: 1.2598715e+08 | T7: 1.2598715e+08 | U7: 1.2598715e+08 | V7: 1.2598715e+08 | W7: 1.2598728e+08 | X7: 1.2598728e+08 | Y7: 1.2598728e+08 | Z7: 1.2598728e+08
A8: 2021 | B8: 1.2987983e+08 | C8: 1.2980125e+08 | D8: 1.2987814e+08 | E8: 1.2987983e+08 | F8: 1.2979955e+08 | G8: 1.2980371e+08 | H8: 1.2988214e+08 | I8: 1.2987998e+08 | J8: 1.2980631e+08 | K8: 1.2980365e+08 | L8: 1.2988464e+08 | M8: 1.2987996e+08 | N8: 1.2980886e+08 | O8: 1.2980125e+08 | P8: 1.2987868e+08 | Q8: 1.2987983e+08 | R8: 1.298001e+08 | S8: 1.2980371e+08 | T8: 1.2988268e+08 | U8: 1.2987998e+08 | V8: 1.2980685e+08 | W8: 1.2980365e+08 | X8: 1.2988518e+08 | Y8: 1.2987995e+08 | Z8: 1.2980941e+08
A9: 2022 | B9: 1.3650808e+08 | C9: 1.3619747e+08 | D9: 1.365012e+08 | E9: 1.3650808e+08 | F9: 1.3619054e+08 | G9: 1.3620733e+08 | H9: 1.3651987e+08 | I9: 1.3650954e+08 | J9: 1.3622097e+08 | K9: 1.3620725e+08 | L9: 1.3653158e+08 | M9: 1.3650968e+08 | N9: 1.3623312e+08 | O9: 1.3619282e+08 | P9: 1.3650308e+08 | Q9: 1.3650808e+08 | R9: 1.3618778e+08 | S9: 1.3620283e+08 | T9: 1.3652176e+08 | U9: 1.3650952e+08 | V9: 1.3621835e+08 | W9: 1.3620276e+08 | X9: 1.3653347e+08 | Y9: 1.3650966e+08 | Z9: 1.3623051e+08
A10: 2023 | B10: 1.4333428e+08 | C10: 1.4270422e+08 | D10: 1.4332005e+08 | E10: 1.4333428e+08 | F10: 1.4268993e+08 | G10: 1.4272429e+08 | H10: 1.4336228e+08 | I10: 1.4333822e+08 | J10: 1.4275693e+08 | K10: 1.4272427e+08 | L10: 1.4338876e+08 | M10: 1.4333867e+08 | N10: 1.4278456e+08 | O10: 1.4268639e+08 | P10: 1.4332296e+08 | Q10: 1.4333428e+08 | R10: 1.4267502e+08 | S10: 1.4270705e+08 | T10: 1.4336521e+08 | U10: 1.4333815e+08 | V10: 1.4274256e+08 | W10: 1.4270705e+08 | X10: 1.433917e+08 | Y10: 1.433386e+08 | Z10: 1.4277023e+08
A11: 2024 | B11: 1.5196078e+08 | C11: 1.5081509e+08 | D11: 1.5193527e+08 | E11: 1.5196078e+08 | F11: 1.5078952e+08 | G11: 1.5085203e+08 | H11: 1.520189e+08 | I11: 1.5196951e+08 | J11: 1.5091951e+08 | K11: 1.5085254e+08 | L11: 1.5207146e+08 | M11: 1.5197081e+08 | N11: 1.5097458e+08 | O11: 1.5076351e+08 | P11: 1.5193836e+08 | Q11: 1.5196078e+08 | R11: 1.5074102e+08 | S11: 1.5080216e+08 | T11: 1.5202201e+08 | U11: 1.5196933e+08 | V11: 1.5087258e+08 | W11: 1.5080274e+08 | X11: 1.5207457e+08 | Y11: 1.5197064e+08 | Z11: 1.5092774e+08
A12: 2025 | B12: 1.5732787e+08 | C12: 1.5558524e+08 | D12: 1.5728896e+08 | E12: 1.5732787e+08 | F12: 1.5554637e+08 | G12: 1.5564179e+08 | H12: 1.5742459e+08 | I12: 1.573428e+08 | J12: 1.5575378e+08 | K12: 1.5564313e+08 | L12: 1.5750988e+08 | M12: 1.5734519e+08 | N12: 1.5584331e+08 | O12: 1.5547825e+08 | P12: 1.5729223e+08 | Q12: 1.5732787e+08 | R12: 1.5544263e+08 | S12: 1.5553837e+08 | T12: 1.5742787e+08 | U12: 1.5734246e+08 | V12: 1.5565329e+08 | W12: 1.5553989e+08 | X12: 1.5751316e+08 | Y12: 1.5734486e+08 | Z12: 1.5574301e+08
A13: 2026 | B13: 1.611743e+08 | C13: 1.5875619e+08 | D13: 1.6112075e+08 | E13: 1.611743e+08 | F13: 1.587029e+08 | G13: 1.5883504e+08 | H13: 1.6131943e+08 | I13: 1.6119716e+08 | J13: 1.5900265e+08 | K13: 1.5883757e+08 | L13: 1.6144442e+08 | M13: 1.6120094e+08 | N13: 1.5913396e+08 | O13: 1.5857245e+08 | P13: 1.6112285e+08 | Q13: 1.611743e+08 | R13: 1.5852124e+08 | S13: 1.5865745e+08 | T13: 1.6132153e+08 | U13: 1.611966e+08 | V13: 1.5882651e+08 | W13: 1.5866034e+08 | X13: 1.6144651e+08 | Y13: 1.6120038e+08 | Z13: 1.5895817e+08
... A37: 2050 | B37: 2.2213448e+08 | C37: 1.9810657e+08 | D37: 2.2153725e+08 | E37: 2.2213448e+08 | F37: 1.9757191e+08 | G37: 1.9898597e+08 | H37: 2.2569789e+08 | I37: 2.2248999e+08 | J37: 2.0250824e+08 | K37: 1.991873e+08 | L37: 2.2832347e+08 | M37: 2.2253324e+08 | N37: 2.0514343e+08 | O37: 1.7978645e+08 | P37: 2.204202e+08 | Q37: 2.2213448e+08 | R37: 1.7838478e+08 | S37: 1.8130559e+08 | T37: 2.2447811e+08 | U37: 2.2245665e+08 | V37: 1.8348813e+08 | W37: 1.8170813e+08 | X37: 2.2703835e+08 | Y37: 2.2249798e+08 | Z37: 1.8606406e+08
B41: Scenario Codes
B42: Baseline
B43: 0 | C43: No additional climate change
B44: Climate Scenarios
B45: 100 | C45: Optimistic
B46: 200 | C46: Pessimistic
B47: EWS Scenarios
B48: 10 | C48: Control
B49: 20 | C49: Status Quo
B50: 30 | C50: Improvement
B51: Channel Scenarios
B52: 1 | C52: DRR
B53: 2 | C53: Agriculture
B54: 3 | C54: Hydro
B55: 4 | C55: ALL
B56: e.g. _222 = Pessimistic StatusQuo Agriculture

Sheet All
B1: Baseline | C1: Control_Optimistic | D1: StatusQuo_Optimistic | E1: Improvement_Optimistic | F1: Control_Pessimistic | G1: StatusQuo_Pessimistic | H1: Improvement_Pessimistic
B2: KHMNYGDPMKTPKN_0 | C2: KHMNYGDPMKTPKN_114 | D2: KHMNYGDPMKTPKN_124 | E2: KHMNYGDPMKTPKN_134 | F2: KHMNYGDPMKTPKN_214 | G2: KHMNYGDPMKTPKN_224 | H2: KHMNYGDPMKTPKN_234 | L2: =C1 -> Control_Optimistic | M2: =D1 -> StatusQuo_Optimistic | N2: =E1 -> Improvement_Optimistic | O2: =F1 -> Control_Pessimistic | P2: =G1 -> StatusQuo_Pessimistic | Q2: =H1 -> Improvement_Pessimistic
A3: 2015 | B3: {=INDEX(MFModRaw!$B$2:$Z$37,_xlfn.XMATCH($A3,MFModRaw!$A$2:$A$37),_xlfn.XMATCH(B$2,MFModRaw!$B$1:$Z$1))} -> 95406125 | C3: {=INDEX(MFModRaw!$B$2:$Z$37,_xlfn.XMATCH($A3,MFModRaw!$A$2:$A$37),_xlfn.XMATCH(C$2,MFModRaw!$B$1:$Z$1))} -> 95406125 | D3: {=INDEX(MFModRaw!$B$2:$Z$37,_xlfn.XMATCH($A3,MFModRaw!$A$2:$A$37),_xlfn.XMATCH(D$2,MFModRaw!$B$1:$Z$1))} -> 95406125 | E3: {=INDEX(MFModRaw!$B$2:$Z$37,_xlfn.XMATCH($A3,MFModRaw!$A$2:$A$37),_xlfn.XMATCH(E$2,MFModRaw!$B$1:$Z$1))} -> 95406125 | F3: {=INDEX(MFModRaw!$B$2:$Z$37,_xlfn.XMATCH($A3,MFModRaw!$A$2:$A$37),_xlfn.XMATCH(F$2,MFModRaw!$B$1:$Z$1))} -> 95406125 | G3: {=INDEX(MFModRaw!$B$2:$Z$37,_xlfn.XMATCH($A3,MFModRaw!$A$2:$A$37),_xlfn.XMATCH(G$2,MFModRaw!$B$1:$Z$1))} -> 95406125 | H3: {=INDEX(MFModRaw!$B$2:$Z$37,_xlfn.XMATCH($A3,MFModRaw!$A$2:$A$37),_xlfn.XMATCH(H$2,MFModRaw!$B$1:$Z$1))} -> 95406125 | K3: 2015 | L3: =C3/$B3-1 -> 0 | M3: =D3/$B3-1 -> 0 | N3: =E3/$B3-1 -> 0 | O3: =F3/$B3-1 -> 0 | P3: =G3/$B3-1 -> 0 | Q3: =H3/$B3-1 -> 0
A4: 2016 | B4: {=INDEX(MFModRaw!$B$2:$Z$37,_xlfn.XMATCH($A4,MFModRaw!$A$2:$A$37),_xlfn.XMATCH(B$2,MFModRaw!$B$1:$Z$1))} -> 1.0294846e+08 | C4: {=INDEX(MFModRaw!$B$2:$Z$37,_xlfn.XMATCH($A4,MFModRaw!$A$2:$A$37),_xlfn.XMATCH(C$2,MFModRaw!$B$1:$Z$1))} -> 1.0294846e+08 | D4: {=INDEX(MFModRaw!$B$2:$Z$37,_xlfn.XMATCH($A4,MFModRaw!$A$2:$A$37),_xlfn.XMATCH(D$2,MFModRaw!$B$1:$Z$1))} -> 1.0294846e+08 | E4: {=INDEX(MFModRaw!$B$2:$Z$37,_xlfn.XMATCH($A4,MFModRaw!$A$2:$A$37),_xlfn.XMATCH(E$2,MFModRaw!$B$1:$Z$1))} -> 1.0294846e+08 | F4: {=INDEX(MFModRaw!$B$2:$Z$37,_xlfn.XMATCH($A4,MFModRaw!$A$2:$A$37),_xlfn.XMATCH(F$2,MFModRaw!$B$1:$Z$1))} -> 1.0294846e+08 | G4: {=INDEX(MFModRaw!$B$2:$Z$37,_xlfn.XMATCH($A4,MFModRaw!$A$2:$A$37),_xlfn.XMATCH(G$2,MFModRaw!$B$1:$Z$1))} -> 1.0294846e+08 | H4: {=INDEX(MFModRaw!$B$2:$Z$37,_xlfn.XMATCH($A4,MFModRaw!$A$2:$A$37),_xlfn.XMATCH(H$2,MFModRaw!$B$1:$Z$1))} -> 1.0294846e+08 | K4: 2016 | L4: =C4/$B4-1 -> 0 | M4: =D4/$B4-1 -> 0 | N4: =E4/$B4-1 -> 0 | O4: =F4/$B4-1 -> 0 | P4: =G4/$B4-1 -> 0 | Q4: =H4/$B4-1 -> 0
A5: 2017 | B5: {=INDEX(MFModRaw!$B$2:$Z$37,_xlfn.XMATCH($A5,MFModRaw!$A$2:$A$37),_xlfn.XMATCH(B$2,MFModRaw!$B$1:$Z$1))} -> 1.1126159e+08 | C5: {=INDEX(MFModRaw!$B$2:$Z$37,_xlfn.XMATCH($A5,MFModRaw!$A$2:$A$37),_xlfn.XMATCH(C$2,MFModRaw!$B$1:$Z$1))} -> 1.1126159e+08 | D5: {=INDEX(MFModRaw!$B$2:$Z$37,_xlfn.XMATCH($A5,MFModRaw!$A$2:$A$37),_xlfn.XMATCH(D$2,MFModRaw!$B$1:$Z$1))} -> 1.1126159e+08 | E5: {=INDEX(MFModRaw!$B$2:$Z$37,_xlfn.XMATCH($A5,MFModRaw!$A$2:$A$37),_xlfn.XMATCH(E$2,MFModRaw!$B$1:$Z$1))} -> 1.1126159e+08 | F5: {=INDEX(MFModRaw!$B$2:$Z$37,_xlfn.XMATCH($A5,MFModRaw!$A$2:$A$37),_xlfn.XMATCH(F$2,MFModRaw!$B$1:$Z$1))} -> 1.1126159e+08 | G5: {=INDEX(MFModRaw!$B$2:$Z$37,_xlfn.XMATCH($A5,MFModRaw!$A$2:$A$37),_xlfn.XMATCH(G$2,MFModRaw!$B$1:$Z$1))} -> 1.1126159e+08 | H5: {=INDEX(MFModRaw!$B$2:$Z$37,_xlfn.XMATCH($A5,MFModRaw!$A$2:$A$37),_xlfn.XMATCH(H$2,MFModRaw!$B$1:$Z$1))} -> 1.1126159e+08 | K5: 2017 | L5: =C5/$B5-1 -> 0 | M5: =D5/$B5-1 -> 0 | N5: =E5/$B5-1 -> 0 | O5: =F5/$B5-1 -> 0 | P5: =G5/$B5-1 -> 0 | Q5: =H5/$B5-1 -> 0
A6: 2018 | B6: {=INDEX(MFModRaw!$B$2:$Z$37,_xlfn.XMATCH($A6,MFModRaw!$A$2:$A$37),_xlfn.XMATCH(B$2,MFModRaw!$B$1:$Z$1))} -> 1.2102615e+08 | C6: {=INDEX(MFModRaw!$B$2:$Z$37,_xlfn.XMATCH($A6,MFModRaw!$A$2:$A$37),_xlfn.XMATCH(C$2,MFModRaw!$B$1:$Z$1))} -> 1.2102615e+08 | D6: {=INDEX(MFModRaw!$B$2:$Z$37,_xlfn.XMATCH($A6,MFModRaw!$A$2:$A$37),_xlfn.XMATCH(D$2,MFModRaw!$B$1:$Z$1))} -> 1.2102615e+08 | E6: {=INDEX(MFModRaw!$B$2:$Z$37,_xlfn.XMATCH($A6,MFModRaw!$A$2:$A$37),_xlfn.XMATCH(E$2,MFModRaw!$B$1:$Z$1))} -> 1.2102615e+08 | F6: {=INDEX(MFModRaw!$B$2:$Z$37,_xlfn.XMATCH($A6,MFModRaw!$A$2:$A$37),_xlfn.XMATCH(F$2,MFModRaw!$B$1:$Z$1))} -> 1.2102615e+08 | G6: {=INDEX(MFModRaw!$B$2:$Z$37,_xlfn.XMATCH($A6,MFModRaw!$A$2:$A$37),_xlfn.XMATCH(G$2,MFModRaw!$B$1:$Z$1))} -> 1.2102615e+08 | H6: {=INDEX(MFModRaw!$B$2:$Z$37,_xlfn.XMATCH($A6,MFModRaw!$A$2:$A$37),_xlfn.XMATCH(H$2,MFModRaw!$B$1:$Z$1))} -> 1.2102615e+08 | K6: 2018 | L6: =C6/$B6-1 -> 0 | M6: =D6/$B6-1 -> 0 | N6: =E6/$B6-1 -> 0 | O6: =F6/$B6-1 -> 0 | P6: =G6/$B6-1 -> 0 | Q6: =H6/$B6-1 -> 0
A7: 2019 | B7: {=INDEX(MFModRaw!$B$2:$Z$37,_xlfn.XMATCH($A7,MFModRaw!$A$2:$A$37),_xlfn.XMATCH(B$2,MFModRaw!$B$1:$Z$1))} -> 1.3063194e+08 | C7: {=INDEX(MFModRaw!$B$2:$Z$37,_xlfn.XMATCH($A7,MFModRaw!$A$2:$A$37),_xlfn.XMATCH(C$2,MFModRaw!$B$1:$Z$1))} -> 1.3063194e+08 | D7: {=INDEX(MFModRaw!$B$2:$Z$37,_xlfn.XMATCH($A7,MFModRaw!$A$2:$A$37),_xlfn.XMATCH(D$2,MFModRaw!$B$1:$Z$1))} -> 1.3063194e+08 | E7: {=INDEX(MFModRaw!$B$2:$Z$37,_xlfn.XMATCH($A7,MFModRaw!$A$2:$A$37),_xlfn.XMATCH(E$2,MFModRaw!$B$1:$Z$1))} -> 1.3063194e+08 | F7: {=INDEX(MFModRaw!$B$2:$Z$37,_xlfn.XMATCH($A7,MFModRaw!$A$2:$A$37),_xlfn.XMATCH(F$2,MFModRaw!$B$1:$Z$1))} -> 1.3063194e+08 | G7: {=INDEX(MFModRaw!$B$2:$Z$37,_xlfn.XMATCH($A7,MFModRaw!$A$2:$A$37),_xlfn.XMATCH(G$2,MFModRaw!$B$1:$Z$1))} -> 1.3063194e+08 | H7: {=INDEX(MFModRaw!$B$2:$Z$37,_xlfn.XMATCH($A7,MFModRaw!$A$2:$A$37),_xlfn.XMATCH(H$2,MFModRaw!$B$1:$Z$1))} -> 1.3063194e+08 | K7: 2019 | L7: =C7/$B7-1 -> 0 | M7: =D7/$B7-1 -> 0 | N7: =E7/$B7-1 -> 0 | O7: =F7/$B7-1 -> 0 | P7: =G7/$B7-1 -> 0 | Q7: =H7/$B7-1 -> 0
A8: 2020 | B8: {=INDEX(MFModRaw!$B$2:$Z$37,_xlfn.XMATCH($A8,MFModRaw!$A$2:$A$37),_xlfn.XMATCH(B$2,MFModRaw!$B$1:$Z$1))} -> 1.2598703e+08 | C8: {=INDEX(MFModRaw!$B$2:$Z$37,_xlfn.XMATCH($A8,MFModRaw!$A$2:$A$37),_xlfn.XMATCH(C$2,MFModRaw!$B$1:$Z$1))} -> 1.2598703e+08 | D8: {=INDEX(MFModRaw!$B$2:$Z$37,_xlfn.XMATCH($A8,MFModRaw!$A$2:$A$37),_xlfn.XMATCH(D$2,MFModRaw!$B$1:$Z$1))} -> 1.2598715e+08 | E8: {=INDEX(MFModRaw!$B$2:$Z$37,_xlfn.XMATCH($A8,MFModRaw!$A$2:$A$37),_xlfn.XMATCH(E$2,MFModRaw!$B$1:$Z$1))} -> 1.2598728e+08 | F8: {=INDEX(MFModRaw!$B$2:$Z$37,_xlfn.XMATCH($A8,MFModRaw!$A$2:$A$37),_xlfn.XMATCH(F$2,MFModRaw!$B$1:$Z$1))} -> 1.2598703e+08 | G8: {=INDEX(MFModRaw!$B$2:$Z$37,_xlfn.XMATCH($A8,MFModRaw!$A$2:$A$37),_xlfn.XMATCH(G$2,MFModRaw!$B$1:$Z$1))} -> 1.2598715e+08 | H8: {=INDEX(MFModRaw!$B$2:$Z$37,_xlfn.XMATCH($A8,MFModRaw!$A$2:$A$37),_xlfn.XMATCH(H$2,MFModRaw!$B$1:$Z$1))} -> 1.2598728e+08 | K8: 2020 | L8: =C8/$B8-1 -> 0 | M8: =D8/$B8-1 -> 9.8388951e-07 | N8: =E8/$B8-1 -> 1.9678185e-06 | O8: =F8/$B8-1 -> 0 | P8: =G8/$B8-1 -> 9.8388951e-07 | Q8: =H8/$B8-1 -> 1.9678185e-06
A9: 2021 | B9: {=INDEX(MFModRaw!$B$2:$Z$37,_xlfn.XMATCH($A9,MFModRaw!$A$2:$A$37),_xlfn.XMATCH(B$2,MFModRaw!$B$1:$Z$1))} -> 1.2987983e+08 | C9: {=INDEX(MFModRaw!$B$2:$Z$37,_xlfn.XMATCH($A9,MFModRaw!$A$2:$A$37),_xlfn.XMATCH(C$2,MFModRaw!$B$1:$Z$1))} -> 1.2979955e+08 | D9: {=INDEX(MFModRaw!$B$2:$Z$37,_xlfn.XMATCH($A9,MFModRaw!$A$2:$A$37),_xlfn.XMATCH(D$2,MFModRaw!$B$1:$Z$1))} -> 1.2980631e+08 | E9: {=INDEX(MFModRaw!$B$2:$Z$37,_xlfn.XMATCH($A9,MFModRaw!$A$2:$A$37),_xlfn.XMATCH(E$2,MFModRaw!$B$1:$Z$1))} -> 1.2980886e+08 | F9: {=INDEX(MFModRaw!$B$2:$Z$37,_xlfn.XMATCH($A9,MFModRaw!$A$2:$A$37),_xlfn.XMATCH(F$2,MFModRaw!$B$1:$Z$1))} -> 1.298001e+08 | G9: {=INDEX(MFModRaw!$B$2:$Z$37,_xlfn.XMATCH($A9,MFModRaw!$A$2:$A$37),_xlfn.XMATCH(G$2,MFModRaw!$B$1:$Z$1))} -> 1.2980685e+08 | H9: {=INDEX(MFModRaw!$B$2:$Z$37,_xlfn.XMATCH($A9,MFModRaw!$A$2:$A$37),_xlfn.XMATCH(H$2,MFModRaw!$B$1:$Z$1))} -> 1.2980941e+08 | K9: 2021 | L9: =C9/$B9-1 -> -0.00061811396 | M9: =D9/$B9-1 -> -0.00056608629 | N9: =E9/$B9-1 -> -0.00054642254 | O9: =F9/$B9-1 -> -0.00061390114 | P9: =G9/$B9-1 -> -0.00056188043 | Q9: =H9/$B9-1 -> -0.00054221004
A10: 2022 | B10: {=INDEX(MFModRaw!$B$2:$Z$37,_xlfn.XMATCH($A10,MFModRaw!$A$2:$A$37),_xlfn.XMATCH(B$2,MFModRaw!$B$1:$Z$1))} -> 1.3650808e+08 | C10: {=INDEX(MFModRaw!$B$2:$Z$37,_xlfn.XMATCH($A10,MFModRaw!$A$2:$A$37),_xlfn.XMATCH(C$2,MFModRaw!$B$1:$Z$1))} -> 1.3619054e+08 | D10: {=INDEX(MFModRaw!$B$2:$Z$37,_xlfn.XMATCH($A10,MFModRaw!$A$2:$A$37),_xlfn.XMATCH(D$2,MFModRaw!$B$1:$Z$1))} -> 1.3622097e+08 | E10: {=INDEX(MFModRaw!$B$2:$Z$37,_xlfn.XMATCH($A10,MFModRaw!$A$2:$A$37),_xlfn.XMATCH(E$2,MFModRaw!$B$1:$Z$1))} -> 1.3623312e+08 | F10: {=INDEX(MFModRaw!$B$2:$Z$37,_xlfn.XMATCH($A10,MFModRaw!$A$2:$A$37),_xlfn.XMATCH(F$2,MFModRaw!$B$1:$Z$1))} -> 1.3618778e+08 | G10: {=INDEX(MFModRaw!$B$2:$Z$37,_xlfn.XMATCH($A10,MFModRaw!$A$2:$A$37),_xlfn.XMATCH(G$2,MFModRaw!$B$1:$Z$1))} -> 1.3621835e+08 | H10: {=INDEX(MFModRaw!$B$2:$Z$37,_xlfn.XMATCH($A10,MFModRaw!$A$2:$A$37),_xlfn.XMATCH(H$2,MFModRaw!$B$1:$Z$1))} -> 1.3623051e+08 | K10: 2022 | L10: =C10/$B10-1 -> -0.0023261383 | M10: =D10/$B10-1 -> -0.0021032237 | N10: =E10/$B10-1 -> -0.0020142114 | O10: =F10/$B10-1 -> -0.0023463452 | P10: =G10/$B10-1 -> -0.0021223937 | Q10: =H10/$B10-1 -> -0.0020333117
A11: 2023 | B11: {=INDEX(MFModRaw!$B$2:$Z$37,_xlfn.XMATCH($A11,MFModRaw!$A$2:$A$37),_xlfn.XMATCH(B$2,MFModRaw!$B$1:$Z$1))} -> 1.4333428e+08 | C11: {=INDEX(MFModRaw!$B$2:$Z$37,_xlfn.XMATCH($A11,MFModRaw!$A$2:$A$37),_xlfn.XMATCH(C$2,MFModRaw!$B$1:$Z$1))} -> 1.4268993e+08 | D11: {=INDEX(MFModRaw!$B$2:$Z$37,_xlfn.XMATCH($A11,MFModRaw!$A$2:$A$37),_xlfn.XMATCH(D$2,MFModRaw!$B$1:$Z$1))} -> 1.4275693e+08 | E11: {=INDEX(MFModRaw!$B$2:$Z$37,_xlfn.XMATCH($A11,MFModRaw!$A$2:$A$37),_xlfn.XMATCH(E$2,MFModRaw!$B$1:$Z$1))} -> 1.4278456e+08 | F11: {=INDEX(MFModRaw!$B$2:$Z$37,_xlfn.XMATCH($A11,MFModRaw!$A$2:$A$37),_xlfn.XMATCH(F$2,MFModRaw!$B$1:$Z$1))} -> 1.4267502e+08 | G11: {=INDEX(MFModRaw!$B$2:$Z$37,_xlfn.XMATCH($A11,MFModRaw!$A$2:$A$37),_xlfn.XMATCH(G$2,MFModRaw!$B$1:$Z$1))} -> 1.4274256e+08 | H11: {=INDEX(MFModRaw!$B$2:$Z$37,_xlfn.XMATCH($A11,MFModRaw!$A$2:$A$37),_xlfn.XMATCH(H$2,MFModRaw!$B$1:$Z$1))} -> 1.4277023e+08 | K11: 2023 | L11: =C11/$B11-1 -> -0.0044954207 | M11: =D11/$B11-1 -> -0.0040279766 | N11: =E11/$B11-1 -> -0.0038352041 | O11: =F11/$B11-1 -> -0.0045994312 | P11: =G11/$B11-1 -> -0.0041282063 | Q11: =H11/$B11-1 -> -0.0039352157
A12: 2024 | B12: {=INDEX(MFModRaw!$B$2:$Z$37,_xlfn.XMATCH($A12,MFModRaw!$A$2:$A$37),_xlfn.XMATCH(B$2,MFModRaw!$B$1:$Z$1))} -> 1.5196078e+08 | C12: {=INDEX(MFModRaw!$B$2:$Z$37,_xlfn.XMATCH($A12,MFModRaw!$A$2:$A$37),_xlfn.XMATCH(C$2,MFModRaw!$B$1:$Z$1))} -> 1.5078952e+08 | D12: {=INDEX(MFModRaw!$B$2:$Z$37,_xlfn.XMATCH($A12,MFModRaw!$A$2:$A$37),_xlfn.XMATCH(D$2,MFModRaw!$B$1:$Z$1))} -> 1.5091951e+08 | E12: {=INDEX(MFModRaw!$B$2:$Z$37,_xlfn.XMATCH($A12,MFModRaw!$A$2:$A$37),_xlfn.XMATCH(E$2,MFModRaw!$B$1:$Z$1))} -> 1.5097458e+08 | F12: {=INDEX(MFModRaw!$B$2:$Z$37,_xlfn.XMATCH($A12,MFModRaw!$A$2:$A$37),_xlfn.XMATCH(F$2,MFModRaw!$B$1:$Z$1))} -> 1.5074102e+08 | G12: {=INDEX(MFModRaw!$B$2:$Z$37,_xlfn.XMATCH($A12,MFModRaw!$A$2:$A$37),_xlfn.XMATCH(G$2,MFModRaw!$B$1:$Z$1))} -> 1.5087258e+08 | H12: {=INDEX(MFModRaw!$B$2:$Z$37,_xlfn.XMATCH($A12,MFModRaw!$A$2:$A$37),_xlfn.XMATCH(H$2,MFModRaw!$B$1:$Z$1))} -> 1.5092774e+08 | K12: 2024 | L12: =C12/$B12-1 -> -0.0077076383 | M12: =D12/$B12-1 -> -0.0068522415 | N12: =E12/$B12-1 -> -0.0064898465 | O12: =F12/$B12-1 -> -0.0080267764 | P12: =G12/$B12-1 -> -0.0071610386 | Q12: =H12/$B12-1 -> -0.0067980629
A13: 2025 | B13: {=INDEX(MFModRaw!$B$2:$Z$37,_xlfn.XMATCH($A13,MFModRaw!$A$2:$A$37),_xlfn.XMATCH(B$2,MFModRaw!$B$1:$Z$1))} -> 1.5732787e+08 | C13: {=INDEX(MFModRaw!$B$2:$Z$37,_xlfn.XMATCH($A13,MFModRaw!$A$2:$A$37),_xlfn.XMATCH(C$2,MFModRaw!$B$1:$Z$1))} -> 1.5554637e+08 | D13: {=INDEX(MFModRaw!$B$2:$Z$37,_xlfn.XMATCH($A13,MFModRaw!$A$2:$A$37),_xlfn.XMATCH(D$2,MFModRaw!$B$1:$Z$1))} -> 1.5575378e+08 | E13: {=INDEX(MFModRaw!$B$2:$Z$37,_xlfn.XMATCH($A13,MFModRaw!$A$2:$A$37),_xlfn.XMATCH(E$2,MFModRaw!$B$1:$Z$1))} -> 1.5584331e+08 | F13: {=INDEX(MFModRaw!$B$2:$Z$37,_xlfn.XMATCH($A13,MFModRaw!$A$2:$A$37),_xlfn.XMATCH(F$2,MFModRaw!$B$1:$Z$1))} -> 1.5544263e+08 | G13: {=INDEX(MFModRaw!$B$2:$Z$37,_xlfn.XMATCH($A13,MFModRaw!$A$2:$A$37),_xlfn.XMATCH(G$2,MFModRaw!$B$1:$Z$1))} -> 1.5565329e+08 | H13: {=INDEX(MFModRaw!$B$2:$Z$37,_xlfn.XMATCH($A13,MFModRaw!$A$2:$A$37),_xlfn.XMATCH(H$2,MFModRaw!$B$1:$Z$1))} -> 1.5574301e+08 | K13: 2025 | L13: =C13/$B13-1 -> -0.011323455 | M13: =D13/$B13-1 -> -0.010005158 | N13: =E13/$B13-1 -> -0.0094360788 | O13: =F13/$B13-1 -> -0.011982869 | P13: =G13/$B13-1 -> -0.010643877 | Q13: =H13/$B13-1 -> -0.010073556
A14: 2026 | B14: {=INDEX(MFModRaw!$B$2:$Z$37,_xlfn.XMATCH($A14,MFModRaw!$A$2:$A$37),_xlfn.XMATCH(B$2,MFModRaw!$B$1:$Z$1))} -> 1.611743e+08 | C14: {=INDEX(MFModRaw!$B$2:$Z$37,_xlfn.XMATCH($A14,MFModRaw!$A$2:$A$37),_xlfn.XMATCH(C$2,MFModRaw!$B$1:$Z$1))} -> 1.587029e+08 | D14: {=INDEX(MFModRaw!$B$2:$Z$37,_xlfn.XMATCH($A14,MFModRaw!$A$2:$A$37),_xlfn.XMATCH(D$2,MFModRaw!$B$1:$Z$1))} -> 1.5900265e+08 | E14: {=INDEX(MFModRaw!$B$2:$Z$37,_xlfn.XMATCH($A14,MFModRaw!$A$2:$A$37),_xlfn.XMATCH(E$2,MFModRaw!$B$1:$Z$1))} -> 1.5913396e+08 | F14: {=INDEX(MFModRaw!$B$2:$Z$37,_xlfn.XMATCH($A14,MFModRaw!$A$2:$A$37),_xlfn.XMATCH(F$2,MFModRaw!$B$1:$Z$1))} -> 1.5852124e+08 | G14: {=INDEX(MFModRaw!$B$2:$Z$37,_xlfn.XMATCH($A14,MFModRaw!$A$2:$A$37),_xlfn.XMATCH(G$2,MFModRaw!$B$1:$Z$1))} -> 1.5882651e+08 | H14: {=INDEX(MFModRaw!$B$2:$Z$37,_xlfn.XMATCH($A14,MFModRaw!$A$2:$A$37),_xlfn.XMATCH(H$2,MFModRaw!$B$1:$Z$1))} -> 1.5895817e+08 | K14: 2026 | L14: =C14/$B14-1 -> -0.015333709 | M14: =D14/$B14-1 -> -0.01347391 | N14: =E14/$B14-1 -> -0.012659158 | O14: =F14/$B14-1 -> -0.016460781 | P14: =G14/$B14-1 -> -0.01456673 | Q14: =H14/$B14-1 -> -0.0137499
... A38: 2050 | B38: {=INDEX(MFModRaw!$B$2:$Z$37,_xlfn.XMATCH($A38,MFModRaw!$A$2:$A$37),_xlfn.XMATCH(B$2,MFModRaw!$B$1:$Z$1))} -> 2.2213448e+08 | C38: {=INDEX(MFModRaw!$B$2:$Z$37,_xlfn.XMATCH($A38,MFModRaw!$A$2:$A$37),_xlfn.XMATCH(C$2,MFModRaw!$B$1:$Z$1))} -> 1.9757191e+08 | D38: {=INDEX(MFModRaw!$B$2:$Z$37,_xlfn.XMATCH($A38,MFModRaw!$A$2:$A$37),_xlfn.XMATCH(D$2,MFModRaw!$B$1:$Z$1))} -> 2.0250824e+08 | E38: {=INDEX(MFModRaw!$B$2:$Z$37,_xlfn.XMATCH($A38,MFModRaw!$A$2:$A$37),_xlfn.XMATCH(E$2,MFModRaw!$B$1:$Z$1))} -> 2.0514343e+08 | F38: {=INDEX(MFModRaw!$B$2:$Z$37,_xlfn.XMATCH($A38,MFModRaw!$A$2:$A$37),_xlfn.XMATCH(F$2,MFModRaw!$B$1:$Z$1))} -> 1.7838478e+08 | G38: {=INDEX(MFModRaw!$B$2:$Z$37,_xlfn.XMATCH($A38,MFModRaw!$A$2:$A$37),_xlfn.XMATCH(G$2,MFModRaw!$B$1:$Z$1))} -> 1.8348813e+08 | H38: {=INDEX(MFModRaw!$B$2:$Z$37,_xlfn.XMATCH($A38,MFModRaw!$A$2:$A$37),_xlfn.XMATCH(H$2,MFModRaw!$B$1:$Z$1))} -> 1.8606406e+08 | K38: 2050 | L38: =C38/$B38-1 -> -0.11057521 | M38: =D38/$B38-1 -> -0.088352958 | N38: =E38/$B38-1 -> -0.076489918 | O38: =F38/$B38-1 -> -0.19695141 | P38: =G38/$B38-1 -> -0.17397728 | Q38: =H38/$B38-1 -> -0.16238102

Sheet DRR
B1: Baseline | C1: Control_Optimistic | D1: StatusQuo_Optimistic | E1: Improvement_Optimistic | F1: Control_Pessimistic | G1: StatusQuo_Pessimistic | H1: Improvement_Pessimistic
B2: KHMNYGDPMKTPKN_0 | C2: KHMNYGDPMKTPKN_111 | D2: KHMNYGDPMKTPKN_121 | E2: KHMNYGDPMKTPKN_131 | F2: KHMNYGDPMKTPKN_211 | G2: KHMNYGDPMKTPKN_221 | H2: KHMNYGDPMKTPKN_231 | L2: =C1 -> Control_Optimistic | M2: =D1 -> StatusQuo_Optimistic | N2: =E1 -> Improvement_Optimistic | O2: =F1 -> Control_Pessimistic | P2: =G1 -> StatusQuo_Pessimistic | Q2: =H1 -> Improvement_Pessimistic
A3: 2015 | B3: {=INDEX(MFModRaw!$B$2:$Z$37,_xlfn.XMATCH($A3,MFModRaw!$A$2:$A$37),_xlfn.XMATCH(B$2,MFModRaw!$B$1:$Z$1))} -> 95406125 | C3: {=INDEX(MFModRaw!$B$2:$Z$37,_xlfn.XMATCH($A3,MFModRaw!$A$2:$A$37),_xlfn.XMATCH(C$2,MFModRaw!$B$1:$Z$1))} -> 95406125 | D3: {=INDEX(MFModRaw!$B$2:$Z$37,_xlfn.XMATCH($A3,MFModRaw!$A$2:$A$37),_xlfn.XMATCH(D$2,MFModRaw!$B$1:$Z$1))} -> 95406125 | E3: {=INDEX(MFModRaw!$B$2:$Z$37,_xlfn.XMATCH($A3,MFModRaw!$A$2:$A$37),_xlfn.XMATCH(E$2,MFModRaw!$B$1:$Z$1))} -> 95406125 | F3: {=INDEX(MFModRaw!$B$2:$Z$37,_xlfn.XMATCH($A3,MFModRaw!$A$2:$A$37),_xlfn.XMATCH(F$2,MFModRaw!$B$1:$Z$1))} -> 95406125 | G3: {=INDEX(MFModRaw!$B$2:$Z$37,_xlfn.XMATCH($A3,MFModRaw!$A$2:$A$37),_xlfn.XMATCH(G$2,MFModRaw!$B$1:$Z$1))} -> 95406125 | H3: {=INDEX(MFModRaw!$B$2:$Z$37,_xlfn.XMATCH($A3,MFModRaw!$A$2:$A$37),_xlfn.XMATCH(H$2,MFModRaw!$B$1:$Z$1))} -> 95406125 | K3: 2015 | L3: =C3/$B3-1 -> 0 | M3: =D3/$B3-1 -> 0 | N3: =E3/$B3-1 -> 0 | O3: =F3/$B3-1 -> 0 | P3: =G3/$B3-1 -> 0 | Q3: =H3/$B3-1 -> 0
A4: 2016 | B4: {=INDEX(MFModRaw!$B$2:$Z$37,_xlfn.XMATCH($A4,MFModRaw!$A$2:$A$37),_xlfn.XMATCH(B$2,MFModRaw!$B$1:$Z$1))} -> 1.0294846e+08 | C4: {=INDEX(MFModRaw!$B$2:$Z$37,_xlfn.XMATCH($A4,MFModRaw!$A$2:$A$37),_xlfn.XMATCH(C$2,MFModRaw!$B$1:$Z$1))} -> 1.0294846e+08 | D4: {=INDEX(MFModRaw!$B$2:$Z$37,_xlfn.XMATCH($A4,MFModRaw!$A$2:$A$37),_xlfn.XMATCH(D$2,MFModRaw!$B$1:$Z$1))} -> 1.0294846e+08 | E4: {=INDEX(MFModRaw!$B$2:$Z$37,_xlfn.XMATCH($A4,MFModRaw!$A$2:$A$37),_xlfn.XMATCH(E$2,MFModRaw!$B$1:$Z$1))} -> 1.0294846e+08 | F4: {=INDEX(MFModRaw!$B$2:$Z$37,_xlfn.XMATCH($A4,MFModRaw!$A$2:$A$37),_xlfn.XMATCH(F$2,MFModRaw!$B$1:$Z$1))} -> 1.0294846e+08 | G4: {=INDEX(MFModRaw!$B$2:$Z$37,_xlfn.XMATCH($A4,MFModRaw!$A$2:$A$37),_xlfn.XMATCH(G$2,MFModRaw!$B$1:$Z$1))} -> 1.0294846e+08 | H4: {=INDEX(MFModRaw!$B$2:$Z$37,_xlfn.XMATCH($A4,MFModRaw!$A$2:$A$37),_xlfn.XMATCH(H$2,MFModRaw!$B$1:$Z$1))} -> 1.0294846e+08 | K4: 2016 | L4: =C4/$B4-1 -> 0 | M4: =D4/$B4-1 -> 0 | N4: =E4/$B4-1 -> 0 | O4: =F4/$B4-1 -> 0 | P4: =G4/$B4-1 -> 0 | Q4: =H4/$B4-1 -> 0
A5: 2017 | B5: {=INDEX(MFModRaw!$B$2:$Z$37,_xlfn.XMATCH($A5,MFModRaw!$A$2:$A$37),_xlfn.XMATCH(B$2,MFModRaw!$B$1:$Z$1))} -> 1.1126159e+08 | C5: {=INDEX(MFModRaw!$B$2:$Z$37,_xlfn.XMATCH($A5,MFModRaw!$A$2:$A$37),_xlfn.XMATCH(C$2,MFModRaw!$B$1:$Z$1))} -> 1.1126159e+08 | D5: {=INDEX(MFModRaw!$B$2:$Z$37,_xlfn.XMATCH($A5,MFModRaw!$A$2:$A$37),_xlfn.XMATCH(D$2,MFModRaw!$B$1:$Z$1))} -> 1.1126159e+08 | E5: {=INDEX(MFModRaw!$B$2:$Z$37,_xlfn.XMATCH($A5,MFModRaw!$A$2:$A$37),_xlfn.XMATCH(E$2,MFModRaw!$B$1:$Z$1))} -> 1.1126159e+08 | F5: {=INDEX(MFModRaw!$B$2:$Z$37,_xlfn.XMATCH($A5,MFModRaw!$A$2:$A$37),_xlfn.XMATCH(F$2,MFModRaw!$B$1:$Z$1))} -> 1.1126159e+08 | G5: {=INDEX(MFModRaw!$B$2:$Z$37,_xlfn.XMATCH($A5,MFModRaw!$A$2:$A$37),_xlfn.XMATCH(G$2,MFModRaw!$B$1:$Z$1))} -> 1.1126159e+08 | H5: {=INDEX(MFModRaw!$B$2:$Z$37,_xlfn.XMATCH($A5,MFModRaw!$A$2:$A$37),_xlfn.XMATCH(H$2,MFModRaw!$B$1:$Z$1))} -> 1.1126159e+08 | K5: 2017 | L5: =C5/$B5-1 -> 0 | M5: =D5/$B5-1 -> 0 | N5: =E5/$B5-1 -> 0 | O5: =F5/$B5-1 -> 0 | P5: =G5/$B5-1 -> 0 | Q5: =H5/$B5-1 -> 0
A6: 2018 | B6: {=INDEX(MFModRaw!$B$2:$Z$37,_xlfn.XMATCH($A6,MFModRaw!$A$2:$A$37),_xlfn.XMATCH(B$2,MFModRaw!$B$1:$Z$1))} -> 1.2102615e+08 | C6: {=INDEX(MFModRaw!$B$2:$Z$37,_xlfn.XMATCH($A6,MFModRaw!$A$2:$A$37),_xlfn.XMATCH(C$2,MFModRaw!$B$1:$Z$1))} -> 1.2102615e+08 | D6: {=INDEX(MFModRaw!$B$2:$Z$37,_xlfn.XMATCH($A6,MFModRaw!$A$2:$A$37),_xlfn.XMATCH(D$2,MFModRaw!$B$1:$Z$1))} -> 1.2102615e+08 | E6: {=INDEX(MFModRaw!$B$2:$Z$37,_xlfn.XMATCH($A6,MFModRaw!$A$2:$A$37),_xlfn.XMATCH(E$2,MFModRaw!$B$1:$Z$1))} -> 1.2102615e+08 | F6: {=INDEX(MFModRaw!$B$2:$Z$37,_xlfn.XMATCH($A6,MFModRaw!$A$2:$A$37),_xlfn.XMATCH(F$2,MFModRaw!$B$1:$Z$1))} -> 1.2102615e+08 | G6: {=INDEX(MFModRaw!$B$2:$Z$37,_xlfn.XMATCH($A6,MFModRaw!$A$2:$A$37),_xlfn.XMATCH(G$2,MFModRaw!$B$1:$Z$1))} -> 1.2102615e+08 | H6: {=INDEX(MFModRaw!$B$2:$Z$37,_xlfn.XMATCH($A6,MFModRaw!$A$2:$A$37),_xlfn.XMATCH(H$2,MFModRaw!$B$1:$Z$1))} -> 1.2102615e+08 | K6: 2018 | L6: =C6/$B6-1 -> 0 | M6: =D6/$B6-1 -> 0 | N6: =E6/$B6-1 -> 0 | O6: =F6/$B6-1 -> 0 | P6: =G6/$B6-1 -> 0 | Q6: =H6/$B6-1 -> 0
A7: 2019 | B7: {=INDEX(MFModRaw!$B$2:$Z$37,_xlfn.XMATCH($A7,MFModRaw!$A$2:$A$37),_xlfn.XMATCH(B$2,MFModRaw!$B$1:$Z$1))} -> 1.3063194e+08 | C7: {=INDEX(MFModRaw!$B$2:$Z$37,_xlfn.XMATCH($A7,MFModRaw!$A$2:$A$37),_xlfn.XMATCH(C$2,MFModRaw!$B$1:$Z$1))} -> 1.3063194e+08 | D7: {=INDEX(MFModRaw!$B$2:$Z$37,_xlfn.XMATCH($A7,MFModRaw!$A$2:$A$37),_xlfn.XMATCH(D$2,MFModRaw!$B$1:$Z$1))} -> 1.3063194e+08 | E7: {=INDEX(MFModRaw!$B$2:$Z$37,_xlfn.XMATCH($A7,MFModRaw!$A$2:$A$37),_xlfn.XMATCH(E$2,MFModRaw!$B$1:$Z$1))} -> 1.3063194e+08 | F7: {=INDEX(MFModRaw!$B$2:$Z$37,_xlfn.XMATCH($A7,MFModRaw!$A$2:$A$37),_xlfn.XMATCH(F$2,MFModRaw!$B$1:$Z$1))} -> 1.3063194e+08 | G7: {=INDEX(MFModRaw!$B$2:$Z$37,_xlfn.XMATCH($A7,MFModRaw!$A$2:$A$37),_xlfn.XMATCH(G$2,MFModRaw!$B$1:$Z$1))} -> 1.3063194e+08 | H7: {=INDEX(MFModRaw!$B$2:$Z$37,_xlfn.XMATCH($A7,MFModRaw!$A$2:$A$37),_xlfn.XMATCH(H$2,MFModRaw!$B$1:$Z$1))} -> 1.3063194e+08 | K7: 2019 | L7: =C7/$B7-1 -> 0 | M7: =D7/$B7-1 -> 0 | N7: =E7/$B7-1 -> 0 | O7: =F7/$B7-1 -> 0 | P7: =G7/$B7-1 -> 0 | Q7: =H7/$B7-1 -> 0
A8: 2020 | B8: {=INDEX(MFModRaw!$B$2:$Z$37,_xlfn.XMATCH($A8,MFModRaw!$A$2:$A$37),_xlfn.XMATCH(B$2,MFModRaw!$B$1:$Z$1))} -> 1.2598703e+08 | C8: {=INDEX(MFModRaw!$B$2:$Z$37,_xlfn.XMATCH($A8,MFModRaw!$A$2:$A$37),_xlfn.XMATCH(C$2,MFModRaw!$B$1:$Z$1))} -> 1.2598703e+08 | D8: {=INDEX(MFModRaw!$B$2:$Z$37,_xlfn.XMATCH($A8,MFModRaw!$A$2:$A$37),_xlfn.XMATCH(D$2,MFModRaw!$B$1:$Z$1))} -> 1.2598715e+08 | E8: {=INDEX(MFModRaw!$B$2:$Z$37,_xlfn.XMATCH($A8,MFModRaw!$A$2:$A$37),_xlfn.XMATCH(E$2,MFModRaw!$B$1:$Z$1))} -> 1.2598728e+08 | F8: {=INDEX(MFModRaw!$B$2:$Z$37,_xlfn.XMATCH($A8,MFModRaw!$A$2:$A$37),_xlfn.XMATCH(F$2,MFModRaw!$B$1:$Z$1))} -> 1.2598703e+08 | G8: {=INDEX(MFModRaw!$B$2:$Z$37,_xlfn.XMATCH($A8,MFModRaw!$A$2:$A$37),_xlfn.XMATCH(G$2,MFModRaw!$B$1:$Z$1))} -> 1.2598715e+08 | H8: {=INDEX(MFModRaw!$B$2:$Z$37,_xlfn.XMATCH($A8,MFModRaw!$A$2:$A$37),_xlfn.XMATCH(H$2,MFModRaw!$B$1:$Z$1))} -> 1.2598728e+08 | K8: 2020 | L8: =C8/$B8-1 -> 0 | M8: =D8/$B8-1 -> 9.8388951e-07 | N8: =E8/$B8-1 -> 1.9678185e-06 | O8: =F8/$B8-1 -> 0 | P8: =G8/$B8-1 -> 9.8388951e-07 | Q8: =H8/$B8-1 -> 1.9678185e-06
A9: 2021 | B9: {=INDEX(MFModRaw!$B$2:$Z$37,_xlfn.XMATCH($A9,MFModRaw!$A$2:$A$37),_xlfn.XMATCH(B$2,MFModRaw!$B$1:$Z$1))} -> 1.2987983e+08 | C9: {=INDEX(MFModRaw!$B$2:$Z$37,_xlfn.XMATCH($A9,MFModRaw!$A$2:$A$37),_xlfn.XMATCH(C$2,MFModRaw!$B$1:$Z$1))} -> 1.2980125e+08 | D9: {=INDEX(MFModRaw!$B$2:$Z$37,_xlfn.XMATCH($A9,MFModRaw!$A$2:$A$37),_xlfn.XMATCH(D$2,MFModRaw!$B$1:$Z$1))} -> 1.2980371e+08 | E9: {=INDEX(MFModRaw!$B$2:$Z$37,_xlfn.XMATCH($A9,MFModRaw!$A$2:$A$37),_xlfn.XMATCH(E$2,MFModRaw!$B$1:$Z$1))} -> 1.2980365e+08 | F9: {=INDEX(MFModRaw!$B$2:$Z$37,_xlfn.XMATCH($A9,MFModRaw!$A$2:$A$37),_xlfn.XMATCH(F$2,MFModRaw!$B$1:$Z$1))} -> 1.2980125e+08 | G9: {=INDEX(MFModRaw!$B$2:$Z$37,_xlfn.XMATCH($A9,MFModRaw!$A$2:$A$37),_xlfn.XMATCH(G$2,MFModRaw!$B$1:$Z$1))} -> 1.2980371e+08 | H9: {=INDEX(MFModRaw!$B$2:$Z$37,_xlfn.XMATCH($A9,MFModRaw!$A$2:$A$37),_xlfn.XMATCH(H$2,MFModRaw!$B$1:$Z$1))} -> 1.2980365e+08 | K9: 2021 | L9: =C9/$B9-1 -> -0.00060500921 | M9: =D9/$B9-1 -> -0.00058607688 | N9: =E9/$B9-1 -> -0.00058653925 | O9: =F9/$B9-1 -> -0.00060500921 | P9: =G9/$B9-1 -> -0.00058607688 | Q9: =H9/$B9-1 -> -0.00058653925
A10: 2022 | B10: {=INDEX(MFModRaw!$B$2:$Z$37,_xlfn.XMATCH($A10,MFModRaw!$A$2:$A$37),_xlfn.XMATCH(B$2,MFModRaw!$B$1:$Z$1))} -> 1.3650808e+08 | C10: {=INDEX(MFModRaw!$B$2:$Z$37,_xlfn.XMATCH($A10,MFModRaw!$A$2:$A$37),_xlfn.XMATCH(C$2,MFModRaw!$B$1:$Z$1))} -> 1.3619747e+08 | D10: {=INDEX(MFModRaw!$B$2:$Z$37,_xlfn.XMATCH($A10,MFModRaw!$A$2:$A$37),_xlfn.XMATCH(D$2,MFModRaw!$B$1:$Z$1))} -> 1.3620733e+08 | E10: {=INDEX(MFModRaw!$B$2:$Z$37,_xlfn.XMATCH($A10,MFModRaw!$A$2:$A$37),_xlfn.XMATCH(E$2,MFModRaw!$B$1:$Z$1))} -> 1.3620725e+08 | F10: {=INDEX(MFModRaw!$B$2:$Z$37,_xlfn.XMATCH($A10,MFModRaw!$A$2:$A$37),_xlfn.XMATCH(F$2,MFModRaw!$B$1:$Z$1))} -> 1.3619282e+08 | G10: {=INDEX(MFModRaw!$B$2:$Z$37,_xlfn.XMATCH($A10,MFModRaw!$A$2:$A$37),_xlfn.XMATCH(G$2,MFModRaw!$B$1:$Z$1))} -> 1.3620283e+08 | H10: {=INDEX(MFModRaw!$B$2:$Z$37,_xlfn.XMATCH($A10,MFModRaw!$A$2:$A$37),_xlfn.XMATCH(H$2,MFModRaw!$B$1:$Z$1))} -> 1.3620276e+08 | K10: 2022 | L10: =C10/$B10-1 -> -0.0022753746 | M10: =D10/$B10-1 -> -0.0022031378 | N10: =E10/$B10-1 -> -0.0022037142 | O10: =F10/$B10-1 -> -0.0023094467 | P10: =G10/$B10-1 -> -0.0022360891 | Q10: =H10/$B10-1 -> -0.0022366436
A11: 2023 | B11: {=INDEX(MFModRaw!$B$2:$Z$37,_xlfn.XMATCH($A11,MFModRaw!$A$2:$A$37),_xlfn.XMATCH(B$2,MFModRaw!$B$1:$Z$1))} -> 1.4333428e+08 | C11: {=INDEX(MFModRaw!$B$2:$Z$37,_xlfn.XMATCH($A11,MFModRaw!$A$2:$A$37),_xlfn.XMATCH(C$2,MFModRaw!$B$1:$Z$1))} -> 1.4270422e+08 | D11: {=INDEX(MFModRaw!$B$2:$Z$37,_xlfn.XMATCH($A11,MFModRaw!$A$2:$A$37),_xlfn.XMATCH(D$2,MFModRaw!$B$1:$Z$1))} -> 1.4272429e+08 | E11: {=INDEX(MFModRaw!$B$2:$Z$37,_xlfn.XMATCH($A11,MFModRaw!$A$2:$A$37),_xlfn.XMATCH(E$2,MFModRaw!$B$1:$Z$1))} -> 1.4272427e+08 | F11: {=INDEX(MFModRaw!$B$2:$Z$37,_xlfn.XMATCH($A11,MFModRaw!$A$2:$A$37),_xlfn.XMATCH(F$2,MFModRaw!$B$1:$Z$1))} -> 1.4268639e+08 | G11: {=INDEX(MFModRaw!$B$2:$Z$37,_xlfn.XMATCH($A11,MFModRaw!$A$2:$A$37),_xlfn.XMATCH(G$2,MFModRaw!$B$1:$Z$1))} -> 1.4270705e+08 | H11: {=INDEX(MFModRaw!$B$2:$Z$37,_xlfn.XMATCH($A11,MFModRaw!$A$2:$A$37),_xlfn.XMATCH(H$2,MFModRaw!$B$1:$Z$1))} -> 1.4270705e+08 | K11: 2023 | L11: =C11/$B11-1 -> -0.0043957149 | M11: =D11/$B11-1 -> -0.0042556714 | N11: =E11/$B11-1 -> -0.0042558378 | O11: =F11/$B11-1 -> -0.0045201082 | P11: =G11/$B11-1 -> -0.0043759589 | Q11: =H11/$B11-1 -> -0.0043760052
A12: 2024 | B12: {=INDEX(MFModRaw!$B$2:$Z$37,_xlfn.XMATCH($A12,MFModRaw!$A$2:$A$37),_xlfn.XMATCH(B$2,MFModRaw!$B$1:$Z$1))} -> 1.5196078e+08 | C12: {=INDEX(MFModRaw!$B$2:$Z$37,_xlfn.XMATCH($A12,MFModRaw!$A$2:$A$37),_xlfn.XMATCH(C$2,MFModRaw!$B$1:$Z$1))} -> 1.5081509e+08 | D12: {=INDEX(MFModRaw!$B$2:$Z$37,_xlfn.XMATCH($A12,MFModRaw!$A$2:$A$37),_xlfn.XMATCH(D$2,MFModRaw!$B$1:$Z$1))} -> 1.5085203e+08 | E12: {=INDEX(MFModRaw!$B$2:$Z$37,_xlfn.XMATCH($A12,MFModRaw!$A$2:$A$37),_xlfn.XMATCH(E$2,MFModRaw!$B$1:$Z$1))} -> 1.5085254e+08 | F12: {=INDEX(MFModRaw!$B$2:$Z$37,_xlfn.XMATCH($A12,MFModRaw!$A$2:$A$37),_xlfn.XMATCH(F$2,MFModRaw!$B$1:$Z$1))} -> 1.5076351e+08 | G12: {=INDEX(MFModRaw!$B$2:$Z$37,_xlfn.XMATCH($A12,MFModRaw!$A$2:$A$37),_xlfn.XMATCH(G$2,MFModRaw!$B$1:$Z$1))} -> 1.5080216e+08 | H12: {=INDEX(MFModRaw!$B$2:$Z$37,_xlfn.XMATCH($A12,MFModRaw!$A$2:$A$37),_xlfn.XMATCH(H$2,MFModRaw!$B$1:$Z$1))} -> 1.5080274e+08 | K12: 2024 | L12: =C12/$B12-1 -> -0.007539386 | M12: =D12/$B12-1 -> -0.007296279 | N12: =E12/$B12-1 -> -0.0072929048 | O12: =F12/$B12-1 -> -0.0078788267 | P12: =G12/$B12-1 -> -0.0076244444 | Q12: =H12/$B12-1 -> -0.0076206191
A13: 2025 | B13: {=INDEX(MFModRaw!$B$2:$Z$37,_xlfn.XMATCH($A13,MFModRaw!$A$2:$A$37),_xlfn.XMATCH(B$2,MFModRaw!$B$1:$Z$1))} -> 1.5732787e+08 | C13: {=INDEX(MFModRaw!$B$2:$Z$37,_xlfn.XMATCH($A13,MFModRaw!$A$2:$A$37),_xlfn.XMATCH(C$2,MFModRaw!$B$1:$Z$1))} -> 1.5558524e+08 | D13: {=INDEX(MFModRaw!$B$2:$Z$37,_xlfn.XMATCH($A13,MFModRaw!$A$2:$A$37),_xlfn.XMATCH(D$2,MFModRaw!$B$1:$Z$1))} -> 1.5564179e+08 | E13: {=INDEX(MFModRaw!$B$2:$Z$37,_xlfn.XMATCH($A13,MFModRaw!$A$2:$A$37),_xlfn.XMATCH(E$2,MFModRaw!$B$1:$Z$1))} -> 1.5564313e+08 | F13: {=INDEX(MFModRaw!$B$2:$Z$37,_xlfn.XMATCH($A13,MFModRaw!$A$2:$A$37),_xlfn.XMATCH(F$2,MFModRaw!$B$1:$Z$1))} -> 1.5547825e+08 | G13: {=INDEX(MFModRaw!$B$2:$Z$37,_xlfn.XMATCH($A13,MFModRaw!$A$2:$A$37),_xlfn.XMATCH(G$2,MFModRaw!$B$1:$Z$1))} -> 1.5553837e+08 | H13: {=INDEX(MFModRaw!$B$2:$Z$37,_xlfn.XMATCH($A13,MFModRaw!$A$2:$A$37),_xlfn.XMATCH(H$2,MFModRaw!$B$1:$Z$1))} -> 1.5553989e+08 | K13: 2025 | L13: =C13/$B13-1 -> -0.011076412 | M13: =D13/$B13-1 -> -0.010716961 | N13: =E13/$B13-1 -> -0.010708447 | O13: =F13/$B13-1 -> -0.011756454 | P13: =G13/$B13-1 -> -0.011374312 | Q13: =H13/$B13-1 -> -0.011364656
A14: 2026 | B14: {=INDEX(MFModRaw!$B$2:$Z$37,_xlfn.XMATCH($A14,MFModRaw!$A$2:$A$37),_xlfn.XMATCH(B$2,MFModRaw!$B$1:$Z$1))} -> 1.611743e+08 | C14: {=INDEX(MFModRaw!$B$2:$Z$37,_xlfn.XMATCH($A14,MFModRaw!$A$2:$A$37),_xlfn.XMATCH(C$2,MFModRaw!$B$1:$Z$1))} -> 1.5875619e+08 | D14: {=INDEX(MFModRaw!$B$2:$Z$37,_xlfn.XMATCH($A14,MFModRaw!$A$2:$A$37),_xlfn.XMATCH(D$2,MFModRaw!$B$1:$Z$1))} -> 1.5883504e+08 | E14: {=INDEX(MFModRaw!$B$2:$Z$37,_xlfn.XMATCH($A14,MFModRaw!$A$2:$A$37),_xlfn.XMATCH(E$2,MFModRaw!$B$1:$Z$1))} -> 1.5883757e+08 | F14: {=INDEX(MFModRaw!$B$2:$Z$37,_xlfn.XMATCH($A14,MFModRaw!$A$2:$A$37),_xlfn.XMATCH(F$2,MFModRaw!$B$1:$Z$1))} -> 1.5857245e+08 | G14: {=INDEX(MFModRaw!$B$2:$Z$37,_xlfn.XMATCH($A14,MFModRaw!$A$2:$A$37),_xlfn.XMATCH(G$2,MFModRaw!$B$1:$Z$1))} -> 1.5865745e+08 | H14: {=INDEX(MFModRaw!$B$2:$Z$37,_xlfn.XMATCH($A14,MFModRaw!$A$2:$A$37),_xlfn.XMATCH(H$2,MFModRaw!$B$1:$Z$1))} -> 1.5866034e+08 | K14: 2026 | L14: =C14/$B14-1 -> -0.015003032 | M14: =D14/$B14-1 -> -0.014513822 | N14: =E14/$B14-1 -> -0.014498132 | O14: =F14/$B14-1 -> -0.016143048 | P14: =G14/$B14-1 -> -0.015615693 | Q14: =H14/$B14-1 -> -0.015597736
... A38: 2050 | B38: {=INDEX(MFModRaw!$B$2:$Z$37,_xlfn.XMATCH($A38,MFModRaw!$A$2:$A$37),_xlfn.XMATCH(B$2,MFModRaw!$B$1:$Z$1))} -> 2.2213448e+08 | C38: {=INDEX(MFModRaw!$B$2:$Z$37,_xlfn.XMATCH($A38,MFModRaw!$A$2:$A$37),_xlfn.XMATCH(C$2,MFModRaw!$B$1:$Z$1))} -> 1.9810657e+08 | D38: {=INDEX(MFModRaw!$B$2:$Z$37,_xlfn.XMATCH($A38,MFModRaw!$A$2:$A$37),_xlfn.XMATCH(D$2,MFModRaw!$B$1:$Z$1))} -> 1.9898597e+08 | E38: {=INDEX(MFModRaw!$B$2:$Z$37,_xlfn.XMATCH($A38,MFModRaw!$A$2:$A$37),_xlfn.XMATCH(E$2,MFModRaw!$B$1:$Z$1))} -> 1.991873e+08 | F38: {=INDEX(MFModRaw!$B$2:$Z$37,_xlfn.XMATCH($A38,MFModRaw!$A$2:$A$37),_xlfn.XMATCH(F$2,MFModRaw!$B$1:$Z$1))} -> 1.7978645e+08 | G38: {=INDEX(MFModRaw!$B$2:$Z$37,_xlfn.XMATCH($A38,MFModRaw!$A$2:$A$37),_xlfn.XMATCH(G$2,MFModRaw!$B$1:$Z$1))} -> 1.8130559e+08 | H38: {=INDEX(MFModRaw!$B$2:$Z$37,_xlfn.XMATCH($A38,MFModRaw!$A$2:$A$37),_xlfn.XMATCH(H$2,MFModRaw!$B$1:$Z$1))} -> 1.8170813e+08 | K38: 2050 | L38: =C38/$B38-1 -> -0.10816829 | M38: =D38/$B38-1 -> -0.10420945 | N38: =E38/$B38-1 -> -0.10330311 | O38: =F38/$B38-1 -> -0.1906414 | P38: =G38/$B38-1 -> -0.18380258 | Q38: =H38/$B38-1 -> -0.18199045

Sheet AGR
B1: Baseline | C1: Control_Optimistic | D1: StatusQuo_Optimistic | E1: Improvement_Optimistic | F1: Control_Pessimistic | G1: StatusQuo_Pessimistic | H1: Improvement_Pessimistic
B2: KHMNYGDPMKTPKN_0 | C2: KHMNYGDPMKTPKN_112 | D2: KHMNYGDPMKTPKN_122 | E2: KHMNYGDPMKTPKN_132 | F2: KHMNYGDPMKTPKN_212 | G2: KHMNYGDPMKTPKN_222 | H2: KHMNYGDPMKTPKN_232 | L2: =C1 -> Control_Optimistic | M2: =D1 -> StatusQuo_Optimistic | N2: =E1 -> Improvement_Optimistic | O2: =F1 -> Control_Pessimistic | P2: =G1 -> StatusQuo_Pessimistic | Q2: =H1 -> Improvement_Pessimistic
A3: 2015 | B3: {=INDEX(MFModRaw!$B$2:$Z$37,_xlfn.XMATCH($A3,MFModRaw!$A$2:$A$37),_xlfn.XMATCH(B$2,MFModRaw!$B$1:$Z$1))} -> 95406125 | C3: {=INDEX(MFModRaw!$B$2:$Z$37,_xlfn.XMATCH($A3,MFModRaw!$A$2:$A$37),_xlfn.XMATCH(C$2,MFModRaw!$B$1:$Z$1))} -> 95406125 | D3: {=INDEX(MFModRaw!$B$2:$Z$37,_xlfn.XMATCH($A3,MFModRaw!$A$2:$A$37),_xlfn.XMATCH(D$2,MFModRaw!$B$1:$Z$1))} -> 95406125 | E3: {=INDEX(MFModRaw!$B$2:$Z$37,_xlfn.XMATCH($A3,MFModRaw!$A$2:$A$37),_xlfn.XMATCH(E$2,MFModRaw!$B$1:$Z$1))} -> 95406125 | F3: {=INDEX(MFModRaw!$B$2:$Z$37,_xlfn.XMATCH($A3,MFModRaw!$A$2:$A$37),_xlfn.XMATCH(F$2,MFModRaw!$B$1:$Z$1))} -> 95406125 | G3: {=INDEX(MFModRaw!$B$2:$Z$37,_xlfn.XMATCH($A3,MFModRaw!$A$2:$A$37),_xlfn.XMATCH(G$2,MFModRaw!$B$1:$Z$1))} -> 95406125 | H3: {=INDEX(MFModRaw!$B$2:$Z$37,_xlfn.XMATCH($A3,MFModRaw!$A$2:$A$37),_xlfn.XMATCH(H$2,MFModRaw!$B$1:$Z$1))} -> 95406125 | K3: 2015 | L3: =C3/$B3-1 -> 0 | M3: =D3/$B3-1 -> 0 | N3: =E3/$B3-1 -> 0 | O3: =F3/$B3-1 -> 0 | P3: =G3/$B3-1 -> 0 | Q3: =H3/$B3-1 -> 0
A4: 2016 | B4: {=INDEX(MFModRaw!$B$2:$Z$37,_xlfn.XMATCH($A4,MFModRaw!$A$2:$A$37),_xlfn.XMATCH(B$2,MFModRaw!$B$1:$Z$1))} -> 1.0294846e+08 | C4: {=INDEX(MFModRaw!$B$2:$Z$37,_xlfn.XMATCH($A4,MFModRaw!$A$2:$A$37),_xlfn.XMATCH(C$2,MFModRaw!$B$1:$Z$1))} -> 1.0294846e+08 | D4: {=INDEX(MFModRaw!$B$2:$Z$37,_xlfn.XMATCH($A4,MFModRaw!$A$2:$A$37),_xlfn.XMATCH(D$2,MFModRaw!$B$1:$Z$1))} -> 1.0294846e+08 | E4: {=INDEX(MFModRaw!$B$2:$Z$37,_xlfn.XMATCH($A4,MFModRaw!$A$2:$A$37),_xlfn.XMATCH(E$2,MFModRaw!$B$1:$Z$1))} -> 1.0294846e+08 | F4: {=INDEX(MFModRaw!$B$2:$Z$37,_xlfn.XMATCH($A4,MFModRaw!$A$2:$A$37),_xlfn.XMATCH(F$2,MFModRaw!$B$1:$Z$1))} -> 1.0294846e+08 | G4: {=INDEX(MFModRaw!$B$2:$Z$37,_xlfn.XMATCH($A4,MFModRaw!$A$2:$A$37),_xlfn.XMATCH(G$2,MFModRaw!$B$1:$Z$1))} -> 1.0294846e+08 | H4: {=INDEX(MFModRaw!$B$2:$Z$37,_xlfn.XMATCH($A4,MFModRaw!$A$2:$A$37),_xlfn.XMATCH(H$2,MFModRaw!$B$1:$Z$1))} -> 1.0294846e+08 | K4: 2016 | L4: =C4/$B4-1 -> 0 | M4: =D4/$B4-1 -> 0 | N4: =E4/$B4-1 -> 0 | O4: =F4/$B4-1 -> 0 | P4: =G4/$B4-1 -> 0 | Q4: =H4/$B4-1 -> 0
A5: 2017 | B5: {=INDEX(MFModRaw!$B$2:$Z$37,_xlfn.XMATCH($A5,MFModRaw!$A$2:$A$37),_xlfn.XMATCH(B$2,MFModRaw!$B$1:$Z$1))} -> 1.1126159e+08 | C5: {=INDEX(MFModRaw!$B$2:$Z$37,_xlfn.XMATCH($A5,MFModRaw!$A$2:$A$37),_xlfn.XMATCH(C$2,MFModRaw!$B$1:$Z$1))} -> 1.1126159e+08 | D5: {=INDEX(MFModRaw!$B$2:$Z$37,_xlfn.XMATCH($A5,MFModRaw!$A$2:$A$37),_xlfn.XMATCH(D$2,MFModRaw!$B$1:$Z$1))} -> 1.1126159e+08 | E5: {=INDEX(MFModRaw!$B$2:$Z$37,_xlfn.XMATCH($A5,MFModRaw!$A$2:$A$37),_xlfn.XMATCH(E$2,MFModRaw!$B$1:$Z$1))} -> 1.1126159e+08 | F5: {=INDEX(MFModRaw!$B$2:$Z$37,_xlfn.XMATCH($A5,MFModRaw!$A$2:$A$37),_xlfn.XMATCH(F$2,MFModRaw!$B$1:$Z$1))} -> 1.1126159e+08 | G5: {=INDEX(MFModRaw!$B$2:$Z$37,_xlfn.XMATCH($A5,MFModRaw!$A$2:$A$37),_xlfn.XMATCH(G$2,MFModRaw!$B$1:$Z$1))} -> 1.1126159e+08 | H5: {=INDEX(MFModRaw!$B$2:$Z$37,_xlfn.XMATCH($A5,MFModRaw!$A$2:$A$37),_xlfn.XMATCH(H$2,MFModRaw!$B$1:$Z$1))} -> 1.1126159e+08 | K5: 2017 | L5: =C5/$B5-1 -> 0 | M5: =D5/$B5-1 -> 0 | N5: =E5/$B5-1 -> 0 | O5: =F5/$B5-1 -> 0 | P5: =G5/$B5-1 -> 0 | Q5: =H5/$B5-1 -> 0
A6: 2018 | B6: {=INDEX(MFModRaw!$B$2:$Z$37,_xlfn.XMATCH($A6,MFModRaw!$A$2:$A$37),_xlfn.XMATCH(B$2,MFModRaw!$B$1:$Z$1))} -> 1.2102615e+08 | C6: {=INDEX(MFModRaw!$B$2:$Z$37,_xlfn.XMATCH($A6,MFModRaw!$A$2:$A$37),_xlfn.XMATCH(C$2,MFModRaw!$B$1:$Z$1))} -> 1.2102615e+08 | D6: {=INDEX(MFModRaw!$B$2:$Z$37,_xlfn.XMATCH($A6,MFModRaw!$A$2:$A$37),_xlfn.XMATCH(D$2,MFModRaw!$B$1:$Z$1))} -> 1.2102615e+08 | E6: {=INDEX(MFModRaw!$B$2:$Z$37,_xlfn.XMATCH($A6,MFModRaw!$A$2:$A$37),_xlfn.XMATCH(E$2,MFModRaw!$B$1:$Z$1))} -> 1.2102615e+08 | F6: {=INDEX(MFModRaw!$B$2:$Z$37,_xlfn.XMATCH($A6,MFModRaw!$A$2:$A$37),_xlfn.XMATCH(F$2,MFModRaw!$B$1:$Z$1))} -> 1.2102615e+08 | G6: {=INDEX(MFModRaw!$B$2:$Z$37,_xlfn.XMATCH($A6,MFModRaw!$A$2:$A$37),_xlfn.XMATCH(G$2,MFModRaw!$B$1:$Z$1))} -> 1.2102615e+08 | H6: {=INDEX(MFModRaw!$B$2:$Z$37,_xlfn.XMATCH($A6,MFModRaw!$A$2:$A$37),_xlfn.XMATCH(H$2,MFModRaw!$B$1:$Z$1))} -> 1.2102615e+08 | K6: 2018 | L6: =C6/$B6-1 -> 0 | M6: =D6/$B6-1 -> 0 | N6: =E6/$B6-1 -> 0 | O6: =F6/$B6-1 -> 0 | P6: =G6/$B6-1 -> 0 | Q6: =H6/$B6-1 -> 0
A7: 2019 | B7: {=INDEX(MFModRaw!$B$2:$Z$37,_xlfn.XMATCH($A7,MFModRaw!$A$2:$A$37),_xlfn.XMATCH(B$2,MFModRaw!$B$1:$Z$1))} -> 1.3063194e+08 | C7: {=INDEX(MFModRaw!$B$2:$Z$37,_xlfn.XMATCH($A7,MFModRaw!$A$2:$A$37),_xlfn.XMATCH(C$2,MFModRaw!$B$1:$Z$1))} -> 1.3063194e+08 | D7: {=INDEX(MFModRaw!$B$2:$Z$37,_xlfn.XMATCH($A7,MFModRaw!$A$2:$A$37),_xlfn.XMATCH(D$2,MFModRaw!$B$1:$Z$1))} -> 1.3063194e+08 | E7: {=INDEX(MFModRaw!$B$2:$Z$37,_xlfn.XMATCH($A7,MFModRaw!$A$2:$A$37),_xlfn.XMATCH(E$2,MFModRaw!$B$1:$Z$1))} -> 1.3063194e+08 | F7: {=INDEX(MFModRaw!$B$2:$Z$37,_xlfn.XMATCH($A7,MFModRaw!$A$2:$A$37),_xlfn.XMATCH(F$2,MFModRaw!$B$1:$Z$1))} -> 1.3063194e+08 | G7: {=INDEX(MFModRaw!$B$2:$Z$37,_xlfn.XMATCH($A7,MFModRaw!$A$2:$A$37),_xlfn.XMATCH(G$2,MFModRaw!$B$1:$Z$1))} -> 1.3063194e+08 | H7: {=INDEX(MFModRaw!$B$2:$Z$37,_xlfn.XMATCH($A7,MFModRaw!$A$2:$A$37),_xlfn.XMATCH(H$2,MFModRaw!$B$1:$Z$1))} -> 1.3063194e+08 | K7: 2019 | L7: =C7/$B7-1 -> 0 | M7: =D7/$B7-1 -> 0 | N7: =E7/$B7-1 -> 0 | O7: =F7/$B7-1 -> 0 | P7: =G7/$B7-1 -> 0 | Q7: =H7/$B7-1 -> 0
A8: 2020 | B8: {=INDEX(MFModRaw!$B$2:$Z$37,_xlfn.XMATCH($A8,MFModRaw!$A$2:$A$37),_xlfn.XMATCH(B$2,MFModRaw!$B$1:$Z$1))} -> 1.2598703e+08 | C8: {=INDEX(MFModRaw!$B$2:$Z$37,_xlfn.XMATCH($A8,MFModRaw!$A$2:$A$37),_xlfn.XMATCH(C$2,MFModRaw!$B$1:$Z$1))} -> 1.2598703e+08 | D8: {=INDEX(MFModRaw!$B$2:$Z$37,_xlfn.XMATCH($A8,MFModRaw!$A$2:$A$37),_xlfn.XMATCH(D$2,MFModRaw!$B$1:$Z$1))} -> 1.2598715e+08 | E8: {=INDEX(MFModRaw!$B$2:$Z$37,_xlfn.XMATCH($A8,MFModRaw!$A$2:$A$37),_xlfn.XMATCH(E$2,MFModRaw!$B$1:$Z$1))} -> 1.2598728e+08 | F8: {=INDEX(MFModRaw!$B$2:$Z$37,_xlfn.XMATCH($A8,MFModRaw!$A$2:$A$37),_xlfn.XMATCH(F$2,MFModRaw!$B$1:$Z$1))} -> 1.2598703e+08 | G8: {=INDEX(MFModRaw!$B$2:$Z$37,_xlfn.XMATCH($A8,MFModRaw!$A$2:$A$37),_xlfn.XMATCH(G$2,MFModRaw!$B$1:$Z$1))} -> 1.2598715e+08 | H8: {=INDEX(MFModRaw!$B$2:$Z$37,_xlfn.XMATCH($A8,MFModRaw!$A$2:$A$37),_xlfn.XMATCH(H$2,MFModRaw!$B$1:$Z$1))} -> 1.2598728e+08 | K8: 2020 | L8: =C8/$B8-1 -> 0 | M8: =D8/$B8-1 -> 9.8388951e-07 | N8: =E8/$B8-1 -> 1.9678185e-06 | O8: =F8/$B8-1 -> 0 | P8: =G8/$B8-1 -> 9.8388951e-07 | Q8: =H8/$B8-1 -> 1.9678185e-06
A9: 2021 | B9: {=INDEX(MFModRaw!$B$2:$Z$37,_xlfn.XMATCH($A9,MFModRaw!$A$2:$A$37),_xlfn.XMATCH(B$2,MFModRaw!$B$1:$Z$1))} -> 1.2987983e+08 | C9: {=INDEX(MFModRaw!$B$2:$Z$37,_xlfn.XMATCH($A9,MFModRaw!$A$2:$A$37),_xlfn.XMATCH(C$2,MFModRaw!$B$1:$Z$1))} -> 1.2987814e+08 | D9: {=INDEX(MFModRaw!$B$2:$Z$37,_xlfn.XMATCH($A9,MFModRaw!$A$2:$A$37),_xlfn.XMATCH(D$2,MFModRaw!$B$1:$Z$1))} -> 1.2988214e+08 | E9: {=INDEX(MFModRaw!$B$2:$Z$37,_xlfn.XMATCH($A9,MFModRaw!$A$2:$A$37),_xlfn.XMATCH(E$2,MFModRaw!$B$1:$Z$1))} -> 1.2988464e+08 | F9: {=INDEX(MFModRaw!$B$2:$Z$37,_xlfn.XMATCH($A9,MFModRaw!$A$2:$A$37),_xlfn.XMATCH(F$2,MFModRaw!$B$1:$Z$1))} -> 1.2987868e+08 | G9: {=INDEX(MFModRaw!$B$2:$Z$37,_xlfn.XMATCH($A9,MFModRaw!$A$2:$A$37),_xlfn.XMATCH(G$2,MFModRaw!$B$1:$Z$1))} -> 1.2988268e+08 | H9: {=INDEX(MFModRaw!$B$2:$Z$37,_xlfn.XMATCH($A9,MFModRaw!$A$2:$A$37),_xlfn.XMATCH(H$2,MFModRaw!$B$1:$Z$1))} -> 1.2988518e+08 | K9: 2021 | L9: =C9/$B9-1 -> -1.3020023e-05 | M9: =D9/$B9-1 -> 1.778853e-05 | N9: =E9/$B9-1 -> 3.7020701e-05 | O9: =F9/$B9-1 -> -8.8348833e-06 | P9: =G9/$B9-1 -> 2.1980927e-05 | Q9: =H9/$B9-1 -> 4.1219533e-05
A10: 2022 | B10: {=INDEX(MFModRaw!$B$2:$Z$37,_xlfn.XMATCH($A10,MFModRaw!$A$2:$A$37),_xlfn.XMATCH(B$2,MFModRaw!$B$1:$Z$1))} -> 1.3650808e+08 | C10: {=INDEX(MFModRaw!$B$2:$Z$37,_xlfn.XMATCH($A10,MFModRaw!$A$2:$A$37),_xlfn.XMATCH(C$2,MFModRaw!$B$1:$Z$1))} -> 1.365012e+08 | D10: {=INDEX(MFModRaw!$B$2:$Z$37,_xlfn.XMATCH($A10,MFModRaw!$A$2:$A$37),_xlfn.XMATCH(D$2,MFModRaw!$B$1:$Z$1))} -> 1.3651987e+08 | E10: {=INDEX(MFModRaw!$B$2:$Z$37,_xlfn.XMATCH($A10,MFModRaw!$A$2:$A$37),_xlfn.XMATCH(E$2,MFModRaw!$B$1:$Z$1))} -> 1.3653158e+08 | F10: {=INDEX(MFModRaw!$B$2:$Z$37,_xlfn.XMATCH($A10,MFModRaw!$A$2:$A$37),_xlfn.XMATCH(F$2,MFModRaw!$B$1:$Z$1))} -> 1.3650308e+08 | G10: {=INDEX(MFModRaw!$B$2:$Z$37,_xlfn.XMATCH($A10,MFModRaw!$A$2:$A$37),_xlfn.XMATCH(G$2,MFModRaw!$B$1:$Z$1))} -> 1.3652176e+08 | H10: {=INDEX(MFModRaw!$B$2:$Z$37,_xlfn.XMATCH($A10,MFModRaw!$A$2:$A$37),_xlfn.XMATCH(H$2,MFModRaw!$B$1:$Z$1))} -> 1.3653347e+08 | K10: 2022 | L10: =C10/$B10-1 -> -5.0395857e-05 | M10: =D10/$B10-1 -> 8.6408451e-05 | N10: =E10/$B10-1 -> 0.0001721688 | O10: =F10/$B10-1 -> -3.6618412e-05 | P10: =G10/$B10-1 -> 0.00010023451 | Q10: =H10/$B10-1 -> 0.00018602686
A11: 2023 | B11: {=INDEX(MFModRaw!$B$2:$Z$37,_xlfn.XMATCH($A11,MFModRaw!$A$2:$A$37),_xlfn.XMATCH(B$2,MFModRaw!$B$1:$Z$1))} -> 1.4333428e+08 | C11: {=INDEX(MFModRaw!$B$2:$Z$37,_xlfn.XMATCH($A11,MFModRaw!$A$2:$A$37),_xlfn.XMATCH(C$2,MFModRaw!$B$1:$Z$1))} -> 1.4332005e+08 | D11: {=INDEX(MFModRaw!$B$2:$Z$37,_xlfn.XMATCH($A11,MFModRaw!$A$2:$A$37),_xlfn.XMATCH(D$2,MFModRaw!$B$1:$Z$1))} -> 1.4336228e+08 | E11: {=INDEX(MFModRaw!$B$2:$Z$37,_xlfn.XMATCH($A11,MFModRaw!$A$2:$A$37),_xlfn.XMATCH(E$2,MFModRaw!$B$1:$Z$1))} -> 1.4338876e+08 | F11: {=INDEX(MFModRaw!$B$2:$Z$37,_xlfn.XMATCH($A11,MFModRaw!$A$2:$A$37),_xlfn.XMATCH(F$2,MFModRaw!$B$1:$Z$1))} -> 1.4332296e+08 | G11: {=INDEX(MFModRaw!$B$2:$Z$37,_xlfn.XMATCH($A11,MFModRaw!$A$2:$A$37),_xlfn.XMATCH(G$2,MFModRaw!$B$1:$Z$1))} -> 1.4336521e+08 | H11: {=INDEX(MFModRaw!$B$2:$Z$37,_xlfn.XMATCH($A11,MFModRaw!$A$2:$A$37),_xlfn.XMATCH(H$2,MFModRaw!$B$1:$Z$1))} -> 1.433917e+08 | K11: 2023 | L11: =C11/$B11-1 -> -9.9269185e-05 | M11: =D11/$B11-1 -> 0.00019536881 | N11: =E11/$B11-1 -> 0.00038013853 | O11: =F11/$B11-1 -> -7.8937898e-05 | P11: =G11/$B11-1 -> 0.00021579198 | Q11: =H11/$B11-1 -> 0.00040062064
A12: 2024 | B12: {=INDEX(MFModRaw!$B$2:$Z$37,_xlfn.XMATCH($A12,MFModRaw!$A$2:$A$37),_xlfn.XMATCH(B$2,MFModRaw!$B$1:$Z$1))} -> 1.5196078e+08 | C12: {=INDEX(MFModRaw!$B$2:$Z$37,_xlfn.XMATCH($A12,MFModRaw!$A$2:$A$37),_xlfn.XMATCH(C$2,MFModRaw!$B$1:$Z$1))} -> 1.5193527e+08 | D12: {=INDEX(MFModRaw!$B$2:$Z$37,_xlfn.XMATCH($A12,MFModRaw!$A$2:$A$37),_xlfn.XMATCH(D$2,MFModRaw!$B$1:$Z$1))} -> 1.520189e+08 | E12: {=INDEX(MFModRaw!$B$2:$Z$37,_xlfn.XMATCH($A12,MFModRaw!$A$2:$A$37),_xlfn.XMATCH(E$2,MFModRaw!$B$1:$Z$1))} -> 1.5207146e+08 | F12: {=INDEX(MFModRaw!$B$2:$Z$37,_xlfn.XMATCH($A12,MFModRaw!$A$2:$A$37),_xlfn.XMATCH(F$2,MFModRaw!$B$1:$Z$1))} -> 1.5193836e+08 | G12: {=INDEX(MFModRaw!$B$2:$Z$37,_xlfn.XMATCH($A12,MFModRaw!$A$2:$A$37),_xlfn.XMATCH(G$2,MFModRaw!$B$1:$Z$1))} -> 1.5202201e+08 | H12: {=INDEX(MFModRaw!$B$2:$Z$37,_xlfn.XMATCH($A12,MFModRaw!$A$2:$A$37),_xlfn.XMATCH(H$2,MFModRaw!$B$1:$Z$1))} -> 1.5207457e+08 | K12: 2024 | L12: =C12/$B12-1 -> -0.00016787462 | M12: =D12/$B12-1 -> 0.00038248171 | N12: =E12/$B12-1 -> 0.00072831913 | O12: =F12/$B12-1 -> -0.00014752301 | P12: =G12/$B12-1 -> 0.00040291318 | Q12: =H12/$B12-1 -> 0.00074880304
A13: 2025 | B13: {=INDEX(MFModRaw!$B$2:$Z$37,_xlfn.XMATCH($A13,MFModRaw!$A$2:$A$37),_xlfn.XMATCH(B$2,MFModRaw!$B$1:$Z$1))} -> 1.5732787e+08 | C13: {=INDEX(MFModRaw!$B$2:$Z$37,_xlfn.XMATCH($A13,MFModRaw!$A$2:$A$37),_xlfn.XMATCH(C$2,MFModRaw!$B$1:$Z$1))} -> 1.5728896e+08 | D13: {=INDEX(MFModRaw!$B$2:$Z$37,_xlfn.XMATCH($A13,MFModRaw!$A$2:$A$37),_xlfn.XMATCH(D$2,MFModRaw!$B$1:$Z$1))} -> 1.5742459e+08 | E13: {=INDEX(MFModRaw!$B$2:$Z$37,_xlfn.XMATCH($A13,MFModRaw!$A$2:$A$37),_xlfn.XMATCH(E$2,MFModRaw!$B$1:$Z$1))} -> 1.5750988e+08 | F13: {=INDEX(MFModRaw!$B$2:$Z$37,_xlfn.XMATCH($A13,MFModRaw!$A$2:$A$37),_xlfn.XMATCH(F$2,MFModRaw!$B$1:$Z$1))} -> 1.5729223e+08 | G13: {=INDEX(MFModRaw!$B$2:$Z$37,_xlfn.XMATCH($A13,MFModRaw!$A$2:$A$37),_xlfn.XMATCH(G$2,MFModRaw!$B$1:$Z$1))} -> 1.5742787e+08 | H13: {=INDEX(MFModRaw!$B$2:$Z$37,_xlfn.XMATCH($A13,MFModRaw!$A$2:$A$37),_xlfn.XMATCH(H$2,MFModRaw!$B$1:$Z$1))} -> 1.5751316e+08 | K13: 2025 | L13: =C13/$B13-1 -> -0.00024726302 | M13: =D13/$B13-1 -> 0.00061480572 | N13: =E13/$B13-1 -> 0.00115689 | O13: =F13/$B13-1 -> -0.00022651938 | P13: =G13/$B13-1 -> 0.00063563179 | Q13: =H13/$B13-1 -> 0.0011777714
A14: 2026 | B14: {=INDEX(MFModRaw!$B$2:$Z$37,_xlfn.XMATCH($A14,MFModRaw!$A$2:$A$37),_xlfn.XMATCH(B$2,MFModRaw!$B$1:$Z$1))} -> 1.611743e+08 | C14: {=INDEX(MFModRaw!$B$2:$Z$37,_xlfn.XMATCH($A14,MFModRaw!$A$2:$A$37),_xlfn.XMATCH(C$2,MFModRaw!$B$1:$Z$1))} -> 1.6112075e+08 | D14: {=INDEX(MFModRaw!$B$2:$Z$37,_xlfn.XMATCH($A14,MFModRaw!$A$2:$A$37),_xlfn.XMATCH(D$2,MFModRaw!$B$1:$Z$1))} -> 1.6131943e+08 | E14: {=INDEX(MFModRaw!$B$2:$Z$37,_xlfn.XMATCH($A14,MFModRaw!$A$2:$A$37),_xlfn.XMATCH(E$2,MFModRaw!$B$1:$Z$1))} -> 1.6144442e+08 | F14: {=INDEX(MFModRaw!$B$2:$Z$37,_xlfn.XMATCH($A14,MFModRaw!$A$2:$A$37),_xlfn.XMATCH(F$2,MFModRaw!$B$1:$Z$1))} -> 1.6112285e+08 | G14: {=INDEX(MFModRaw!$B$2:$Z$37,_xlfn.XMATCH($A14,MFModRaw!$A$2:$A$37),_xlfn.XMATCH(G$2,MFModRaw!$B$1:$Z$1))} -> 1.6132153e+08 | H14: {=INDEX(MFModRaw!$B$2:$Z$37,_xlfn.XMATCH($A14,MFModRaw!$A$2:$A$37),_xlfn.XMATCH(H$2,MFModRaw!$B$1:$Z$1))} -> 1.6144651e+08 | K14: 2026 | L14: =C14/$B14-1 -> -0.00033220208 | M14: =D14/$B14-1 -> 0.00090050362 | N14: =E14/$B14-1 -> 0.001675962 | O14: =F14/$B14-1 -> -0.00031917953 | P14: =G14/$B14-1 -> 0.0009134822 | Q14: =H14/$B14-1 -> 0.0016889159
... A38: 2050 | B38: {=INDEX(MFModRaw!$B$2:$Z$37,_xlfn.XMATCH($A38,MFModRaw!$A$2:$A$37),_xlfn.XMATCH(B$2,MFModRaw!$B$1:$Z$1))} -> 2.2213448e+08 | C38: {=INDEX(MFModRaw!$B$2:$Z$37,_xlfn.XMATCH($A38,MFModRaw!$A$2:$A$37),_xlfn.XMATCH(C$2,MFModRaw!$B$1:$Z$1))} -> 2.2153725e+08 | D38: {=INDEX(MFModRaw!$B$2:$Z$37,_xlfn.XMATCH($A38,MFModRaw!$A$2:$A$37),_xlfn.XMATCH(D$2,MFModRaw!$B$1:$Z$1))} -> 2.2569789e+08 | E38: {=INDEX(MFModRaw!$B$2:$Z$37,_xlfn.XMATCH($A38,MFModRaw!$A$2:$A$37),_xlfn.XMATCH(E$2,MFModRaw!$B$1:$Z$1))} -> 2.2832347e+08 | F38: {=INDEX(MFModRaw!$B$2:$Z$37,_xlfn.XMATCH($A38,MFModRaw!$A$2:$A$37),_xlfn.XMATCH(F$2,MFModRaw!$B$1:$Z$1))} -> 2.204202e+08 | G38: {=INDEX(MFModRaw!$B$2:$Z$37,_xlfn.XMATCH($A38,MFModRaw!$A$2:$A$37),_xlfn.XMATCH(G$2,MFModRaw!$B$1:$Z$1))} -> 2.2447811e+08 | H38: {=INDEX(MFModRaw!$B$2:$Z$37,_xlfn.XMATCH($A38,MFModRaw!$A$2:$A$37),_xlfn.XMATCH(H$2,MFModRaw!$B$1:$Z$1))} -> 2.2703835e+08 | K38: 2050 | L38: =C38/$B38-1 -> -0.0026886034 | M38: =D38/$B38-1 -> 0.016041691 | N38: =E38/$B38-1 -> 0.02786144 | O38: =F38/$B38-1 -> -0.0077172941 | P38: =G38/$B38-1 -> 0.010550487 | Q38: =H38/$B38-1 -> 0.022076125

Sheet HYD
B1: Baseline | C1: Control_Optimistic | D1: StatusQuo_Optimistic | E1: Improvement_Optimistic | F1: Control_Pessimistic | G1: StatusQuo_Pessimistic | H1: Improvement_Pessimistic
B2: KHMNYGDPMKTPKN_0 | C2: KHMNYGDPMKTPKN_113 | D2: KHMNYGDPMKTPKN_123 | E2: KHMNYGDPMKTPKN_133 | F2: KHMNYGDPMKTPKN_213 | G2: KHMNYGDPMKTPKN_223 | H2: KHMNYGDPMKTPKN_233 | L2: =C1 -> Control_Optimistic | M2: =D1 -> StatusQuo_Optimistic | N2: =E1 -> Improvement_Optimistic | O2: =F1 -> Control_Pessimistic | P2: =G1 -> StatusQuo_Pessimistic | Q2: =H1 -> Improvement_Pessimistic
A3: 2015 | B3: {=INDEX(MFModRaw!$B$2:$Z$37,_xlfn.XMATCH($A3,MFModRaw!$A$2:$A$37),_xlfn.XMATCH(B$2,MFModRaw!$B$1:$Z$1))} -> 95406125 | C3: {=INDEX(MFModRaw!$B$2:$Z$37,_xlfn.XMATCH($A3,MFModRaw!$A$2:$A$37),_xlfn.XMATCH(C$2,MFModRaw!$B$1:$Z$1))} -> 95406125 | D3: {=INDEX(MFModRaw!$B$2:$Z$37,_xlfn.XMATCH($A3,MFModRaw!$A$2:$A$37),_xlfn.XMATCH(D$2,MFModRaw!$B$1:$Z$1))} -> 95406125 | E3: {=INDEX(MFModRaw!$B$2:$Z$37,_xlfn.XMATCH($A3,MFModRaw!$A$2:$A$37),_xlfn.XMATCH(E$2,MFModRaw!$B$1:$Z$1))} -> 95406125 | F3: {=INDEX(MFModRaw!$B$2:$Z$37,_xlfn.XMATCH($A3,MFModRaw!$A$2:$A$37),_xlfn.XMATCH(F$2,MFModRaw!$B$1:$Z$1))} -> 95406125 | G3: {=INDEX(MFModRaw!$B$2:$Z$37,_xlfn.XMATCH($A3,MFModRaw!$A$2:$A$37),_xlfn.XMATCH(G$2,MFModRaw!$B$1:$Z$1))} -> 95406125 | H3: {=INDEX(MFModRaw!$B$2:$Z$37,_xlfn.XMATCH($A3,MFModRaw!$A$2:$A$37),_xlfn.XMATCH(H$2,MFModRaw!$B$1:$Z$1))} -> 95406125 | K3: 2015 | L3: =C3/$B3-1 -> 0 | M3: =D3/$B3-1 -> 0 | N3: =E3/$B3-1 -> 0 | O3: =F3/$B3-1 -> 0 | P3: =G3/$B3-1 -> 0 | Q3: =H3/$B3-1 -> 0
A4: 2016 | B4: {=INDEX(MFModRaw!$B$2:$Z$37,_xlfn.XMATCH($A4,MFModRaw!$A$2:$A$37),_xlfn.XMATCH(B$2,MFModRaw!$B$1:$Z$1))} -> 1.0294846e+08 | C4: {=INDEX(MFModRaw!$B$2:$Z$37,_xlfn.XMATCH($A4,MFModRaw!$A$2:$A$37),_xlfn.XMATCH(C$2,MFModRaw!$B$1:$Z$1))} -> 1.0294846e+08 | D4: {=INDEX(MFModRaw!$B$2:$Z$37,_xlfn.XMATCH($A4,MFModRaw!$A$2:$A$37),_xlfn.XMATCH(D$2,MFModRaw!$B$1:$Z$1))} -> 1.0294846e+08 | E4: {=INDEX(MFModRaw!$B$2:$Z$37,_xlfn.XMATCH($A4,MFModRaw!$A$2:$A$37),_xlfn.XMATCH(E$2,MFModRaw!$B$1:$Z$1))} -> 1.0294846e+08 | F4: {=INDEX(MFModRaw!$B$2:$Z$37,_xlfn.XMATCH($A4,MFModRaw!$A$2:$A$37),_xlfn.XMATCH(F$2,MFModRaw!$B$1:$Z$1))} -> 1.0294846e+08 | G4: {=INDEX(MFModRaw!$B$2:$Z$37,_xlfn.XMATCH($A4,MFModRaw!$A$2:$A$37),_xlfn.XMATCH(G$2,MFModRaw!$B$1:$Z$1))} -> 1.0294846e+08 | H4: {=INDEX(MFModRaw!$B$2:$Z$37,_xlfn.XMATCH($A4,MFModRaw!$A$2:$A$37),_xlfn.XMATCH(H$2,MFModRaw!$B$1:$Z$1))} -> 1.0294846e+08 | K4: 2016 | L4: =C4/$B4-1 -> 0 | M4: =D4/$B4-1 -> 0 | N4: =E4/$B4-1 -> 0 | O4: =F4/$B4-1 -> 0 | P4: =G4/$B4-1 -> 0 | Q4: =H4/$B4-1 -> 0
A5: 2017 | B5: {=INDEX(MFModRaw!$B$2:$Z$37,_xlfn.XMATCH($A5,MFModRaw!$A$2:$A$37),_xlfn.XMATCH(B$2,MFModRaw!$B$1:$Z$1))} -> 1.1126159e+08 | C5: {=INDEX(MFModRaw!$B$2:$Z$37,_xlfn.XMATCH($A5,MFModRaw!$A$2:$A$37),_xlfn.XMATCH(C$2,MFModRaw!$B$1:$Z$1))} -> 1.1126159e+08 | D5: {=INDEX(MFModRaw!$B$2:$Z$37,_xlfn.XMATCH($A5,MFModRaw!$A$2:$A$37),_xlfn.XMATCH(D$2,MFModRaw!$B$1:$Z$1))} -> 1.1126159e+08 | E5: {=INDEX(MFModRaw!$B$2:$Z$37,_xlfn.XMATCH($A5,MFModRaw!$A$2:$A$37),_xlfn.XMATCH(E$2,MFModRaw!$B$1:$Z$1))} -> 1.1126159e+08 | F5: {=INDEX(MFModRaw!$B$2:$Z$37,_xlfn.XMATCH($A5,MFModRaw!$A$2:$A$37),_xlfn.XMATCH(F$2,MFModRaw!$B$1:$Z$1))} -> 1.1126159e+08 | G5: {=INDEX(MFModRaw!$B$2:$Z$37,_xlfn.XMATCH($A5,MFModRaw!$A$2:$A$37),_xlfn.XMATCH(G$2,MFModRaw!$B$1:$Z$1))} -> 1.1126159e+08 | H5: {=INDEX(MFModRaw!$B$2:$Z$37,_xlfn.XMATCH($A5,MFModRaw!$A$2:$A$37),_xlfn.XMATCH(H$2,MFModRaw!$B$1:$Z$1))} -> 1.1126159e+08 | K5: 2017 | L5: =C5/$B5-1 -> 0 | M5: =D5/$B5-1 -> 0 | N5: =E5/$B5-1 -> 0 | O5: =F5/$B5-1 -> 0 | P5: =G5/$B5-1 -> 0 | Q5: =H5/$B5-1 -> 0
A6: 2018 | B6: {=INDEX(MFModRaw!$B$2:$Z$37,_xlfn.XMATCH($A6,MFModRaw!$A$2:$A$37),_xlfn.XMATCH(B$2,MFModRaw!$B$1:$Z$1))} -> 1.2102615e+08 | C6: {=INDEX(MFModRaw!$B$2:$Z$37,_xlfn.XMATCH($A6,MFModRaw!$A$2:$A$37),_xlfn.XMATCH(C$2,MFModRaw!$B$1:$Z$1))} -> 1.2102615e+08 | D6: {=INDEX(MFModRaw!$B$2:$Z$37,_xlfn.XMATCH($A6,MFModRaw!$A$2:$A$37),_xlfn.XMATCH(D$2,MFModRaw!$B$1:$Z$1))} -> 1.2102615e+08 | E6: {=INDEX(MFModRaw!$B$2:$Z$37,_xlfn.XMATCH($A6,MFModRaw!$A$2:$A$37),_xlfn.XMATCH(E$2,MFModRaw!$B$1:$Z$1))} -> 1.2102615e+08 | F6: {=INDEX(MFModRaw!$B$2:$Z$37,_xlfn.XMATCH($A6,MFModRaw!$A$2:$A$37),_xlfn.XMATCH(F$2,MFModRaw!$B$1:$Z$1))} -> 1.2102615e+08 | G6: {=INDEX(MFModRaw!$B$2:$Z$37,_xlfn.XMATCH($A6,MFModRaw!$A$2:$A$37),_xlfn.XMATCH(G$2,MFModRaw!$B$1:$Z$1))} -> 1.2102615e+08 | H6: {=INDEX(MFModRaw!$B$2:$Z$37,_xlfn.XMATCH($A6,MFModRaw!$A$2:$A$37),_xlfn.XMATCH(H$2,MFModRaw!$B$1:$Z$1))} -> 1.2102615e+08 | K6: 2018 | L6: =C6/$B6-1 -> 0 | M6: =D6/$B6-1 -> 0 | N6: =E6/$B6-1 -> 0 | O6: =F6/$B6-1 -> 0 | P6: =G6/$B6-1 -> 0 | Q6: =H6/$B6-1 -> 0
A7: 2019 | B7: {=INDEX(MFModRaw!$B$2:$Z$37,_xlfn.XMATCH($A7,MFModRaw!$A$2:$A$37),_xlfn.XMATCH(B$2,MFModRaw!$B$1:$Z$1))} -> 1.3063194e+08 | C7: {=INDEX(MFModRaw!$B$2:$Z$37,_xlfn.XMATCH($A7,MFModRaw!$A$2:$A$37),_xlfn.XMATCH(C$2,MFModRaw!$B$1:$Z$1))} -> 1.3063194e+08 | D7: {=INDEX(MFModRaw!$B$2:$Z$37,_xlfn.XMATCH($A7,MFModRaw!$A$2:$A$37),_xlfn.XMATCH(D$2,MFModRaw!$B$1:$Z$1))} -> 1.3063194e+08 | E7: {=INDEX(MFModRaw!$B$2:$Z$37,_xlfn.XMATCH($A7,MFModRaw!$A$2:$A$37),_xlfn.XMATCH(E$2,MFModRaw!$B$1:$Z$1))} -> 1.3063194e+08 | F7: {=INDEX(MFModRaw!$B$2:$Z$37,_xlfn.XMATCH($A7,MFModRaw!$A$2:$A$37),_xlfn.XMATCH(F$2,MFModRaw!$B$1:$Z$1))} -> 1.3063194e+08 | G7: {=INDEX(MFModRaw!$B$2:$Z$37,_xlfn.XMATCH($A7,MFModRaw!$A$2:$A$37),_xlfn.XMATCH(G$2,MFModRaw!$B$1:$Z$1))} -> 1.3063194e+08 | H7: {=INDEX(MFModRaw!$B$2:$Z$37,_xlfn.XMATCH($A7,MFModRaw!$A$2:$A$37),_xlfn.XMATCH(H$2,MFModRaw!$B$1:$Z$1))} -> 1.3063194e+08 | K7: 2019 | L7: =C7/$B7-1 -> 0 | M7: =D7/$B7-1 -> 0 | N7: =E7/$B7-1 -> 0 | O7: =F7/$B7-1 -> 0 | P7: =G7/$B7-1 -> 0 | Q7: =H7/$B7-1 -> 0
A8: 2020 | B8: {=INDEX(MFModRaw!$B$2:$Z$37,_xlfn.XMATCH($A8,MFModRaw!$A$2:$A$37),_xlfn.XMATCH(B$2,MFModRaw!$B$1:$Z$1))} -> 1.2598703e+08 | C8: {=INDEX(MFModRaw!$B$2:$Z$37,_xlfn.XMATCH($A8,MFModRaw!$A$2:$A$37),_xlfn.XMATCH(C$2,MFModRaw!$B$1:$Z$1))} -> 1.2598703e+08 | D8: {=INDEX(MFModRaw!$B$2:$Z$37,_xlfn.XMATCH($A8,MFModRaw!$A$2:$A$37),_xlfn.XMATCH(D$2,MFModRaw!$B$1:$Z$1))} -> 1.2598715e+08 | E8: {=INDEX(MFModRaw!$B$2:$Z$37,_xlfn.XMATCH($A8,MFModRaw!$A$2:$A$37),_xlfn.XMATCH(E$2,MFModRaw!$B$1:$Z$1))} -> 1.2598728e+08 | F8: {=INDEX(MFModRaw!$B$2:$Z$37,_xlfn.XMATCH($A8,MFModRaw!$A$2:$A$37),_xlfn.XMATCH(F$2,MFModRaw!$B$1:$Z$1))} -> 1.2598703e+08 | G8: {=INDEX(MFModRaw!$B$2:$Z$37,_xlfn.XMATCH($A8,MFModRaw!$A$2:$A$37),_xlfn.XMATCH(G$2,MFModRaw!$B$1:$Z$1))} -> 1.2598715e+08 | H8: {=INDEX(MFModRaw!$B$2:$Z$37,_xlfn.XMATCH($A8,MFModRaw!$A$2:$A$37),_xlfn.XMATCH(H$2,MFModRaw!$B$1:$Z$1))} -> 1.2598728e+08 | K8: 2020 | L8: =C8/$B8-1 -> 0 | M8: =D8/$B8-1 -> 9.8388951e-07 | N8: =E8/$B8-1 -> 1.9678185e-06 | O8: =F8/$B8-1 -> 0 | P8: =G8/$B8-1 -> 9.8388951e-07 | Q8: =H8/$B8-1 -> 1.9678185e-06
A9: 2021 | B9: {=INDEX(MFModRaw!$B$2:$Z$37,_xlfn.XMATCH($A9,MFModRaw!$A$2:$A$37),_xlfn.XMATCH(B$2,MFModRaw!$B$1:$Z$1))} -> 1.2987983e+08 | C9: {=INDEX(MFModRaw!$B$2:$Z$37,_xlfn.XMATCH($A9,MFModRaw!$A$2:$A$37),_xlfn.XMATCH(C$2,MFModRaw!$B$1:$Z$1))} -> 1.2987983e+08 | D9: {=INDEX(MFModRaw!$B$2:$Z$37,_xlfn.XMATCH($A9,MFModRaw!$A$2:$A$37),_xlfn.XMATCH(D$2,MFModRaw!$B$1:$Z$1))} -> 1.2987998e+08 | E9: {=INDEX(MFModRaw!$B$2:$Z$37,_xlfn.XMATCH($A9,MFModRaw!$A$2:$A$37),_xlfn.XMATCH(E$2,MFModRaw!$B$1:$Z$1))} -> 1.2987996e+08 | F9: {=INDEX(MFModRaw!$B$2:$Z$37,_xlfn.XMATCH($A9,MFModRaw!$A$2:$A$37),_xlfn.XMATCH(F$2,MFModRaw!$B$1:$Z$1))} -> 1.2987983e+08 | G9: {=INDEX(MFModRaw!$B$2:$Z$37,_xlfn.XMATCH($A9,MFModRaw!$A$2:$A$37),_xlfn.XMATCH(G$2,MFModRaw!$B$1:$Z$1))} -> 1.2987998e+08 | H9: {=INDEX(MFModRaw!$B$2:$Z$37,_xlfn.XMATCH($A9,MFModRaw!$A$2:$A$37),_xlfn.XMATCH(H$2,MFModRaw!$B$1:$Z$1))} -> 1.2987995e+08 | K9: 2021 | L9: =C9/$B9-1 -> -3.0423508e-10 | M9: =D9/$B9-1 -> 1.1749876e-06 | N9: =E9/$B9-1 -> 9.7507189e-07 | O9: =F9/$B9-1 -> -3.0423508e-10 | P9: =G9/$B9-1 -> 1.1579758e-06 | Q9: =H9/$B9-1 -> 9.5852285e-07
A10: 2022 | B10: {=INDEX(MFModRaw!$B$2:$Z$37,_xlfn.XMATCH($A10,MFModRaw!$A$2:$A$37),_xlfn.XMATCH(B$2,MFModRaw!$B$1:$Z$1))} -> 1.3650808e+08 | C10: {=INDEX(MFModRaw!$B$2:$Z$37,_xlfn.XMATCH($A10,MFModRaw!$A$2:$A$37),_xlfn.XMATCH(C$2,MFModRaw!$B$1:$Z$1))} -> 1.3650808e+08 | D10: {=INDEX(MFModRaw!$B$2:$Z$37,_xlfn.XMATCH($A10,MFModRaw!$A$2:$A$37),_xlfn.XMATCH(D$2,MFModRaw!$B$1:$Z$1))} -> 1.3650954e+08 | E10: {=INDEX(MFModRaw!$B$2:$Z$37,_xlfn.XMATCH($A10,MFModRaw!$A$2:$A$37),_xlfn.XMATCH(E$2,MFModRaw!$B$1:$Z$1))} -> 1.3650968e+08 | F10: {=INDEX(MFModRaw!$B$2:$Z$37,_xlfn.XMATCH($A10,MFModRaw!$A$2:$A$37),_xlfn.XMATCH(F$2,MFModRaw!$B$1:$Z$1))} -> 1.3650808e+08 | G10: {=INDEX(MFModRaw!$B$2:$Z$37,_xlfn.XMATCH($A10,MFModRaw!$A$2:$A$37),_xlfn.XMATCH(G$2,MFModRaw!$B$1:$Z$1))} -> 1.3650952e+08 | H10: {=INDEX(MFModRaw!$B$2:$Z$37,_xlfn.XMATCH($A10,MFModRaw!$A$2:$A$37),_xlfn.XMATCH(H$2,MFModRaw!$B$1:$Z$1))} -> 1.3650966e+08 | K10: 2022 | L10: =C10/$B10-1 -> 1.8558599e-10 | M10: =D10/$B10-1 -> 1.0740812e-05 | N10: =E10/$B10-1 -> 1.1742747e-05 | O10: =F10/$B10-1 -> 1.8558599e-10 | P10: =G10/$B10-1 -> 1.0562678e-05 | Q10: =H10/$B10-1 -> 1.1586817e-05
A11: 2023 | B11: {=INDEX(MFModRaw!$B$2:$Z$37,_xlfn.XMATCH($A11,MFModRaw!$A$2:$A$37),_xlfn.XMATCH(B$2,MFModRaw!$B$1:$Z$1))} -> 1.4333428e+08 | C11: {=INDEX(MFModRaw!$B$2:$Z$37,_xlfn.XMATCH($A11,MFModRaw!$A$2:$A$37),_xlfn.XMATCH(C$2,MFModRaw!$B$1:$Z$1))} -> 1.4333428e+08 | D11: {=INDEX(MFModRaw!$B$2:$Z$37,_xlfn.XMATCH($A11,MFModRaw!$A$2:$A$37),_xlfn.XMATCH(D$2,MFModRaw!$B$1:$Z$1))} -> 1.4333822e+08 | E11: {=INDEX(MFModRaw!$B$2:$Z$37,_xlfn.XMATCH($A11,MFModRaw!$A$2:$A$37),_xlfn.XMATCH(E$2,MFModRaw!$B$1:$Z$1))} -> 1.4333867e+08 | F11: {=INDEX(MFModRaw!$B$2:$Z$37,_xlfn.XMATCH($A11,MFModRaw!$A$2:$A$37),_xlfn.XMATCH(F$2,MFModRaw!$B$1:$Z$1))} -> 1.4333428e+08 | G11: {=INDEX(MFModRaw!$B$2:$Z$37,_xlfn.XMATCH($A11,MFModRaw!$A$2:$A$37),_xlfn.XMATCH(G$2,MFModRaw!$B$1:$Z$1))} -> 1.4333815e+08 | H11: {=INDEX(MFModRaw!$B$2:$Z$37,_xlfn.XMATCH($A11,MFModRaw!$A$2:$A$37),_xlfn.XMATCH(H$2,MFModRaw!$B$1:$Z$1))} -> 1.433386e+08 | K11: 2023 | L11: =C11/$B11-1 -> 4.13789e-11 | M11: =D11/$B11-1 -> 2.749186e-05 | N11: =E11/$B11-1 -> 3.0616654e-05 | O11: =F11/$B11-1 -> 4.13789e-11 | P11: =G11/$B11-1 -> 2.6990124e-05 | Q11: =H11/$B11-1 -> 3.0140511e-05
A12: 2024 | B12: {=INDEX(MFModRaw!$B$2:$Z$37,_xlfn.XMATCH($A12,MFModRaw!$A$2:$A$37),_xlfn.XMATCH(B$2,MFModRaw!$B$1:$Z$1))} -> 1.5196078e+08 | C12: {=INDEX(MFModRaw!$B$2:$Z$37,_xlfn.XMATCH($A12,MFModRaw!$A$2:$A$37),_xlfn.XMATCH(C$2,MFModRaw!$B$1:$Z$1))} -> 1.5196078e+08 | D12: {=INDEX(MFModRaw!$B$2:$Z$37,_xlfn.XMATCH($A12,MFModRaw!$A$2:$A$37),_xlfn.XMATCH(D$2,MFModRaw!$B$1:$Z$1))} -> 1.5196951e+08 | E12: {=INDEX(MFModRaw!$B$2:$Z$37,_xlfn.XMATCH($A12,MFModRaw!$A$2:$A$37),_xlfn.XMATCH(E$2,MFModRaw!$B$1:$Z$1))} -> 1.5197081e+08 | F12: {=INDEX(MFModRaw!$B$2:$Z$37,_xlfn.XMATCH($A12,MFModRaw!$A$2:$A$37),_xlfn.XMATCH(F$2,MFModRaw!$B$1:$Z$1))} -> 1.5196078e+08 | G12: {=INDEX(MFModRaw!$B$2:$Z$37,_xlfn.XMATCH($A12,MFModRaw!$A$2:$A$37),_xlfn.XMATCH(G$2,MFModRaw!$B$1:$Z$1))} -> 1.5196933e+08 | H12: {=INDEX(MFModRaw!$B$2:$Z$37,_xlfn.XMATCH($A12,MFModRaw!$A$2:$A$37),_xlfn.XMATCH(H$2,MFModRaw!$B$1:$Z$1))} -> 1.5197064e+08 | K12: 2024 | L12: =C12/$B12-1 -> -1.9655993e-09 | M12: =D12/$B12-1 -> 5.7435824e-05 | N12: =E12/$B12-1 -> 6.6033659e-05 | O12: =F12/$B12-1 -> -1.9655993e-09 | P12: =G12/$B12-1 -> 5.6289531e-05 | Q12: =H12/$B12-1 -> 6.4903184e-05
A13: 2025 | B13: {=INDEX(MFModRaw!$B$2:$Z$37,_xlfn.XMATCH($A13,MFModRaw!$A$2:$A$37),_xlfn.XMATCH(B$2,MFModRaw!$B$1:$Z$1))} -> 1.5732787e+08 | C13: {=INDEX(MFModRaw!$B$2:$Z$37,_xlfn.XMATCH($A13,MFModRaw!$A$2:$A$37),_xlfn.XMATCH(C$2,MFModRaw!$B$1:$Z$1))} -> 1.5732787e+08 | D13: {=INDEX(MFModRaw!$B$2:$Z$37,_xlfn.XMATCH($A13,MFModRaw!$A$2:$A$37),_xlfn.XMATCH(D$2,MFModRaw!$B$1:$Z$1))} -> 1.573428e+08 | E13: {=INDEX(MFModRaw!$B$2:$Z$37,_xlfn.XMATCH($A13,MFModRaw!$A$2:$A$37),_xlfn.XMATCH(E$2,MFModRaw!$B$1:$Z$1))} -> 1.5734519e+08 | F13: {=INDEX(MFModRaw!$B$2:$Z$37,_xlfn.XMATCH($A13,MFModRaw!$A$2:$A$37),_xlfn.XMATCH(F$2,MFModRaw!$B$1:$Z$1))} -> 1.5732787e+08 | G13: {=INDEX(MFModRaw!$B$2:$Z$37,_xlfn.XMATCH($A13,MFModRaw!$A$2:$A$37),_xlfn.XMATCH(G$2,MFModRaw!$B$1:$Z$1))} -> 1.5734246e+08 | H13: {=INDEX(MFModRaw!$B$2:$Z$37,_xlfn.XMATCH($A13,MFModRaw!$A$2:$A$37),_xlfn.XMATCH(H$2,MFModRaw!$B$1:$Z$1))} -> 1.5734486e+08 | K13: 2025 | L13: =C13/$B13-1 -> 1.6805046e-10 | M13: =D13/$B13-1 -> 9.4912214e-05 | N13: =E13/$B13-1 -> 0.00011010556 | O13: =F13/$B13-1 -> 1.6805046e-10 | P13: =G13/$B13-1 -> 9.2784293e-05 | Q13: =H13/$B13-1 -> 0.00010798587
A14: 2026 | B14: {=INDEX(MFModRaw!$B$2:$Z$37,_xlfn.XMATCH($A14,MFModRaw!$A$2:$A$37),_xlfn.XMATCH(B$2,MFModRaw!$B$1:$Z$1))} -> 1.611743e+08 | C14: {=INDEX(MFModRaw!$B$2:$Z$37,_xlfn.XMATCH($A14,MFModRaw!$A$2:$A$37),_xlfn.XMATCH(C$2,MFModRaw!$B$1:$Z$1))} -> 1.611743e+08 | D14: {=INDEX(MFModRaw!$B$2:$Z$37,_xlfn.XMATCH($A14,MFModRaw!$A$2:$A$37),_xlfn.XMATCH(D$2,MFModRaw!$B$1:$Z$1))} -> 1.6119716e+08 | E14: {=INDEX(MFModRaw!$B$2:$Z$37,_xlfn.XMATCH($A14,MFModRaw!$A$2:$A$37),_xlfn.XMATCH(E$2,MFModRaw!$B$1:$Z$1))} -> 1.6120094e+08 | F14: {=INDEX(MFModRaw!$B$2:$Z$37,_xlfn.XMATCH($A14,MFModRaw!$A$2:$A$37),_xlfn.XMATCH(F$2,MFModRaw!$B$1:$Z$1))} -> 1.611743e+08 | G14: {=INDEX(MFModRaw!$B$2:$Z$37,_xlfn.XMATCH($A14,MFModRaw!$A$2:$A$37),_xlfn.XMATCH(G$2,MFModRaw!$B$1:$Z$1))} -> 1.611966e+08 | H14: {=INDEX(MFModRaw!$B$2:$Z$37,_xlfn.XMATCH($A14,MFModRaw!$A$2:$A$37),_xlfn.XMATCH(H$2,MFModRaw!$B$1:$Z$1))} -> 1.6120038e+08 | K14: 2026 | L14: =C14/$B14-1 -> 8.4622664e-10 | M14: =D14/$B14-1 -> 0.00014188637 | N14: =E14/$B14-1 -> 0.00016531698 | O14: =F14/$B14-1 -> 8.4622664e-10 | P14: =G14/$B14-1 -> 0.00013841393 | Q14: =H14/$B14-1 -> 0.0001618418
... A38: 2050 | B38: {=INDEX(MFModRaw!$B$2:$Z$37,_xlfn.XMATCH($A38,MFModRaw!$A$2:$A$37),_xlfn.XMATCH(B$2,MFModRaw!$B$1:$Z$1))} -> 2.2213448e+08 | C38: {=INDEX(MFModRaw!$B$2:$Z$37,_xlfn.XMATCH($A38,MFModRaw!$A$2:$A$37),_xlfn.XMATCH(C$2,MFModRaw!$B$1:$Z$1))} -> 2.2213448e+08 | D38: {=INDEX(MFModRaw!$B$2:$Z$37,_xlfn.XMATCH($A38,MFModRaw!$A$2:$A$37),_xlfn.XMATCH(D$2,MFModRaw!$B$1:$Z$1))} -> 2.2248999e+08 | E38: {=INDEX(MFModRaw!$B$2:$Z$37,_xlfn.XMATCH($A38,MFModRaw!$A$2:$A$37),_xlfn.XMATCH(E$2,MFModRaw!$B$1:$Z$1))} -> 2.2253324e+08 | F38: {=INDEX(MFModRaw!$B$2:$Z$37,_xlfn.XMATCH($A38,MFModRaw!$A$2:$A$37),_xlfn.XMATCH(F$2,MFModRaw!$B$1:$Z$1))} -> 2.2213448e+08 | G38: {=INDEX(MFModRaw!$B$2:$Z$37,_xlfn.XMATCH($A38,MFModRaw!$A$2:$A$37),_xlfn.XMATCH(G$2,MFModRaw!$B$1:$Z$1))} -> 2.2245665e+08 | H38: {=INDEX(MFModRaw!$B$2:$Z$37,_xlfn.XMATCH($A38,MFModRaw!$A$2:$A$37),_xlfn.XMATCH(H$2,MFModRaw!$B$1:$Z$1))} -> 2.2249798e+08 | K38: 2050 | L38: =C38/$B38-1 -> 6.743206e-11 | M38: =D38/$B38-1 -> 0.0016004308 | N38: =E38/$B38-1 -> 0.0017951353 | O38: =F38/$B38-1 -> 6.743206e-11 | P38: =G38/$B38-1 -> 0.001450316 | Q38: =H38/$B38-1 -> 0.0016363812

Sheet INPUT_DRR
A1: Info: | B1: values denote the percentage of total national capital stock destroyed through floods
A2: Climate scenario | B2: Optimistic | E2: Pessimistic
A3: Forecast scenario | B3: Control | C3: Status quo | D3: Improvement | E3: Control | F3: Status quo | G3: Improvement
A4: Year
A5: 2020 | B5: 0.929 | C5: 0.89945701 | D5: 0.89945701 | E5: 0.929 | F5: 0.89945701 | G5: 0.89945701
A6: 2021 | B6: 0.93784211 | C6: 0.90757607 | D6: 0.90698918 | E6: 0.97717731 | F6: 0.94564185 | G6: 0.94503035
A7: 2022 | B7: 0.94289474 | C7: 0.91202141 | D7: 0.91084131 | E7: 1.015212 | F7: 0.9819708 | G7: 0.9807002
A8: 2023 | B8: 0.94747368 | C8: 0.91600403 | D8: 0.91422529 | E8: 1.065925 | F8: 1.0305211 | G8: 1.0285199
A9: 2024 | B9: 0.95015789 | C9: 0.91815143 | D9: 0.91577306 | E9: 1.1128345 | F9: 1.0753482 | G9: 1.0725626
A10: 2025 | B10: 0.95521053 | C10: 0.92258382 | D10: 0.91959505 | E10: 1.1394588 | F10: 1.1005388 | G10: 1.0969735
A11: 2026 | B11: 0.95663158 | C11: 0.92350563 | D11: 0.91991377 | E11: 1.181297 | F11: 1.1403914 | G11: 1.135956
A12: 2027 | B12: 0.95694737 | C12: 0.92335962 | D12: 0.91916774 | E12: 1.2345456 | F12: 1.1912144 | G12: 1.1858066
A13: 2028 | B13: 0.96136842 | C13: 0.92717256 | D13: 0.92235971 | E13: 1.267509 | F13: 1.2224237 | G13: 1.2160782
A14: 2029 | B14: 0.96436842 | C14: 0.9296115 | D14: 0.92418014 | E14: 1.3372393 | F14: 1.2890437 | G14: 1.2815123
A15: 2030 | B15: 0.96421053 | C15: 0.92900502 | D15: 0.92297116 | E15: 1.3803453 | F15: 1.3299458 | G15: 1.3213078
A16: 2031 | B16: 0.96326316 | C16: 0.92763841 | D16: 0.92100768 | E16: 1.3980949 | F16: 1.3463885 | G16: 1.3367646
... A35: 2050 | B35: 1.013 | C35: 0.96646776 | D35: 0.94745024 | E35: 2.974 | F35: 2.8373891 | G35: 2.7815568

Sheet INPUT_HYD
A1: Info: | B1: values are percent cost reductions of electricity generation cost in comparison to the control scenario
A2: Climate scenario | B2: Optimistic / Pessimistic | C2: Optimistic | E2: Pessimistic
A3: Forecast scenario | B3: Control | C3: Status quo | D3: Improvement | E3: Status quo | F3: Improvement
A4: Year
A5: 2020 | B5: 0 | C5: 0 | D5: 0 | E5: 0 | F5: 0
A6: 2021 | B6: 0 | C6: 0.26038898 | D6: 0.30687519 | E6: 0.25771137 | F6: 0.30421234
A7: 2022 | B7: 0 | C7: 0.52383155 | D7: 0.61673203 | E7: 0.51541369 | F7: 0.60833956
A8: 2023 | B8: 0 | C8: 0.78989828 | D8: 0.92915123 | E8: 0.77310244 | F8: 0.91233912
A9: 2024 | B9: 0 | C9: 1.0564421 | D9: 1.2420363 | E9: 1.0307809 | F9: 1.2162422
A10: 2025 | B10: 0 | C10: 1.3281866 | D10: 1.5599995 | E10: 1.2884603 | F10: 1.5201538
A11: 2026 | B11: 0 | C11: 1.5964004 | D11: 1.8745152 | E11: 1.5461225 | F11: 1.8239037
A12: 2027 | B12: 0 | C12: 1.8631351 | D12: 2.1875866 | E12: 1.8037653 | F12: 2.1274707
A13: 2028 | B13: 0 | C13: 2.1399848 | D13: 2.5105348 | E13: 2.0614147 | F13: 2.4311
A14: 2029 | B14: 0 | C14: 2.4156417 | D14: 2.8323182 | E14: 2.3190169 | F14: 2.7342853
A15: 2030 | B15: 0 | C15: 2.6835692 | D15: 3.1465544 | E15: 2.5766342 | F15: 3.0376125
A16: 2031 | B16: 0 | C16: 2.9487771 | D16: 3.458135 | E16: 2.8342744 | F16: 3.3411553
... A35: 2050 | B35: 0 | C35: 8.4929999 | D35: 9.8715369 | E35: 7.7242163 | F35: 9.0593453

Sheet INPUT_AGR
A1: Info: | B1: values are the agricultural productivity change w.r.t. the 2020 control level in percent
A2: Climate scenario | B2: Optimistic | E2: Pessimistic
A3: Forecast scenario | B3: Control | C3: Status quo | D3: Improvement | E3: Control | F3: Status quo | G3: Improvement
A4: Year
A5: 2020 | B5: 0 | C5: 0 | D5: 0 | E5: 0 | F5: 0 | G5: 0
A6: 2021 | B6: -0.14316525 | C6: 0.20100797 | D6: 0.41803016 | E6: -0.097147848 | F6: 0.24718398 | G6: 0.46430618
A7: 2022 | B7: -0.22497396 | C7: 0.46280855 | D7: 0.89649733 | E7: -0.17384352 | F7: 0.51429145 | G7: 0.94820248
A8: 2023 | B8: -0.29911311 | C8: 0.73179406 | D8: 1.3818438 | E8: -0.27610441 | F8: 0.75504067 | G8: 1.4052405
A9: 2024 | B9: -0.34257399 | C9: 1.0313697 | D9: 1.8977249 | E9: -0.37069574 | F9: 1.0028603 | G9: 1.868971
A10: 2025 | B10: -0.4243827 | C10: 1.2916371 | D10: 2.3736921 | E10: -0.4243827 | F10: 1.2916371 | G10: 2.3736921
A11: 2026 | B11: -0.44739141 | C11: 1.6113565 | D11: 2.9095226 | E11: -0.50874794 | F11: 1.5487312 | G11: 2.8460971
A12: 2027 | B12: -0.45250445 | C12: 1.9492448 | D12: 3.463694 | E12: -0.61612188 | F12: 1.7816798 | G12: 3.2936399
A13: 2028 | B13: -0.52408707 | C13: 2.2187954 | D13: 3.94835 | E13: -0.68259146 | F13: 2.0559206 | G13: 3.7827192
A14: 2029 | B14: -0.572661 | C14: 2.5115751 | D14: 4.4563738 | E14: -0.83516797 | F14: 2.2409251 | G14: 4.1805892
A15: 2030 | B15: -0.57010448 | C15: 2.8569126 | D15: 5.0178557 | E15: -0.93074727 | F15: 2.4838396 | G15: 4.6369447
A16: 2031 | B16: -0.55476534 | C16: 3.215535 | D16: 5.5929391 | E16: -0.97010346 | F16: 2.78445 | G16: 5.1519247
... A35: 2050 | B35: -1.4255107 | C35: 8.7670915 | D35: 15.194148 | E35: -4.5228954 | F35: 5.3494372 | G35: 11.574544

Sheet INPUT_COSTS
A1: Info: | B1: All values in 2025 USD
A2: Cost type | B2: OPEX | H2: CAPEX
A3: Climate scenario | B3: Optimistic | E3: Pessimistic | H3: Optimistic | K3: Pessimistic
A4: Forecast scenario | B4: Control | C4: Status quo | D4: Improvement | E4: Control | F4: Status quo | G4: Improvement | H4: Control | I4: Status quo | J4: Improvement | K4: Control | L4: Status quo | M4: Improvement
A5: Year
A6: 2020 | B6: 0 | C6: 500000 | D6: 1000000 | E6: 0 | F6: 500000 | G6: 1000000 | H6: 0 | I6: 0 | J6: 0 | K6: 0 | L6: 0 | M6: 0
A7: 2021 | B7: 0 | C7: 500000 | D7: 1000000 | E7: 0 | F7: 500000 | G7: 1000000 | H7: 0 | I7: 0 | J7: 0 | K7: 0 | L7: 0 | M7: 0
A8: 2022 | B8: 0 | C8: 500000 | D8: 1000000 | E8: 0 | F8: 500000 | G8: 1000000 | H8: 0 | I8: 0 | J8: 0 | K8: 0 | L8: 0 | M8: 0
A9: 2023 | B9: 0 | C9: 500000 | D9: 1000000 | E9: 0 | F9: 500000 | G9: 1000000 | H9: 0 | I9: 0 | J9: 0 | K9: 0 | L9: 0 | M9: 0
A10: 2024 | B10: 0 | C10: 500000 | D10: 1000000 | E10: 0 | F10: 500000 | G10: 1000000 | H10: 0 | I10: 0 | J10: 0 | K10: 0 | L10: 0 | M10: 0
A11: 2025 | B11: 0 | C11: 500000 | D11: 1000000 | E11: 0 | F11: 500000 | G11: 1000000 | H11: 0 | I11: 0 | J11: 0 | K11: 0 | L11: 0 | M11: 0
A12: 2026 | B12: 0 | C12: 500000 | D12: 1000000 | E12: 0 | F12: 500000 | G12: 1000000 | H12: 0 | I12: 0 | J12: 0 | K12: 0 | L12: 0 | M12: 0
A13: 2027 | B13: 0 | C13: 500000 | D13: 1000000 | E13: 0 | F13: 500000 | G13: 1000000 | H13: 0 | I13: 0 | J13: 0 | K13: 0 | L13: 0 | M13: 0
A14: 2028 | B14: 0 | C14: 500000 | D14: 1000000 | E14: 0 | F14: 500000 | G14: 1000000 | H14: 0 | I14: 0 | J14: 0 | K14: 0 | L14: 0 | M14: 0
A15: 2029 | B15: 0 | C15: 500000 | D15: 1000000 | E15: 0 | F15: 500000 | G15: 1000000 | H15: 0 | I15: 0 | J15: 0 | K15: 0 | L15: 0 | M15: 0
A16: 2030 | B16: 0 | C16: 500000 | D16: 1000000 | E16: 0 | F16: 500000 | G16: 1000000 | H16: 0 | I16: 0 | J16: 0 | K16: 0 | L16: 0 | M16: 0
A17: 2031 | B17: 0 | C17: 500000 | D17: 1000000 | E17: 0 | F17: 500000 | G17: 1000000 | H17: 0 | I17: 0 | J17: 4200000 | K17: 0 | L17: 0 | M17: 4200000
... A36: 2050 | B36: 0 | C36: 500000 | D36: 1000000 | E36: 0 | F36: 500000 | G36: 1000000 | H36: 0 | I36: 0 | J36: 0 | K36: 0 | L36: 0 | M36: 0
